{"6ubrychfilip_": [120436.75, "https://www.investopedia.com/simulator/games/user-portfolio?portfolio=10449073", []], "3bergantaro": [116624.22, "https://www.investopedia.com/simulator/games/user-portfolio?portfolio=10445355", []], "5nguyenethan": [124618.88, "https://www.investopedia.com/simulator/games/user-portfolio?portfolio=10445735", [["MANU", "$18.03", "4.46%"], ["PZZA", "$51.22", "-13.26%"]]], "miatarabichi": [136101.34, "https://www.investopedia.com/simulator/games/user-portfolio?portfolio=10445334", [["AMZN", "$206.22", "9.77%"], ["AVGO", "$175.75", "6.62%"], ["HOOD", "$32.60", "37.44%"], ["MSTR", "$342.55", "93.29%"], ["MU", "$103.22", "-6.08%"], ["NVDA", "$147.97", "18.76%"], ["PLTR", "$59.03", "59.64%"]]], "2petergeorge": [116988.53, "https://www.investopedia.com/simulator/games/user-portfolio?portfolio=10447833", []], "3awyonglinus": [101834.51, "https://www.investopedia.com/simulator/games/user-portfolio?portfolio=10445349", [["BABA", "$91.75", "-8.25%"], ["QQQ", "$512.73", "7.70%"]]], "3jubertcolin": [118214.84, "https://www.investopedia.com/simulator/games/user-portfolio?portfolio=10445350", [["ABNB", "$134.16", "9.09%"], ["ADBE", "$523.40", "-1.52%"], ["AMD", "$144.35", "-12.86%"], ["ANF", "$139.11", "-16.17%"], ["APDN", "$0.19", "-91.81%"], ["ASML", "$669.26", "-4.56%"], ["ASTS", "$24.38", "-12.48%"], ["BAC", "$46.20", "20.42%"], ["BIDU", "$84.87", "-1.82%"], ["CMG", "$60.40", "11.57%"], ["DUOL", "$317.73", "25.44%"], ["GLD", "$240.01", "-5.21%"], ["GOOG", "$181.22", "14.88%"], ["LLY", "$815.68", "-13.66%"], ["LMT", "$567.36", "1.61%"], ["META", "$585.01", "10.06%"], ["NVDA", "$147.97", "24.91%"], ["QQQ", "$512.73", "5.56%"], ["RDDT", "$127.50", "14.24%"], ["SNY", "$50.34", "-12.57%"], ["WDC", "$64.13", "4.30%"]]], "2laumei": [113529.83, "https://www.investopedia.com/simulator/games/user-portfolio?portfolio=10447810", [["DJT", "$30.25", "-28.16%"], ["LLY", "$815.68", "-12.03%"], ["NKE", "$76.50", "-6.90%"], ["NVDA", "$147.97", "18.53%"], ["TSLA", "$339.40", "44.34%"]]], "brandens": [116158.39, "https://www.investopedia.com/simulator/games/user-portfolio?portfolio=10447831", [["AAPL", "$225.28", "1.86%"], ["AMZN", "$206.26", "21.58%"], ["BROS", "$49.27", "40.06%"], ["CMG", "$60.40", "14.38%"], ["FLNC", "$20.34", "21.29%"], ["GE", "$181.59", "6.25%"], ["MSFT", "$420.40", "0.67%"], ["NIO", "$4.63", "-19.42%"], ["NVDA", "$147.97", "27.12%"], ["TSLA", "$339.40", "52.10%"], ["WOK", "$5.73", "-21.51%"]]], "3tomaszewskiadrian": [111662.05, "https://www.investopedia.com/simulator/games/user-portfolio?portfolio=10445328", [["AMD", "$144.21", "-12.17%"], ["ARM", "$139.77", "-2.44%"], ["ASML", "$669.26", "-5.87%"], ["CCJ", "$52.29", "1.54%"], ["CRWD", "$337.26", "8.42%"], ["RKLB", "$14.65", "30.35%"]]], "6xusophie": [116284.52, "https://www.investopedia.com/simulator/games/user-portfolio?portfolio=10449079", [["BA", "$144.82", "-17.09%"], ["DB", "$16.73", "6.77%"], ["GOOG", "$181.26", "8.18%"], ["RTX", "$122.88", "3.85%"], ["TGT", "$155.94", "7.16%"], ["UAL", "$87.68", "105.92%"]]], "5wangkyan": [115140.02, "https://www.investopedia.com/simulator/games/user-portfolio?portfolio=10445739", [["BABA", "$91.75", "-5.95%"], ["TSLA", "$339.40", "14.14%"]]], "2gibsonjacob": [111350.92, "https://www.investopedia.com/simulator/games/user-portfolio?portfolio=10447829", [["AAPL", "$225.25", "1.86%"], ["AMZN", "$206.22", "21.54%"], ["LULU", "$318.24", "31.51%"], ["NVDA", "$147.97", "24.10%"], ["PEP", "$164.33", "-4.63%"]]], "1enriquezmario": [143203.55, "https://www.investopedia.com/simulator/games/user-portfolio?portfolio=10445928", [["LUNR", "$10.53", "16.50%"]]], "6hernandezbrady": [86421.46, "https://www.investopedia.com/simulator/games/user-portfolio?portfolio=10449080", [["LUNR", "$10.39", "-1.68%"], ["SKYT", "$8.32", "-0.83%"]]], "unknovus": [134841.36, "https://www.investopedia.com/simulator/games/user-portfolio?portfolio=10450904", [["APP", "$282.69", "29.84%"], ["CRWD", "$337.26", "2.77%"], ["ELF", "$129.44", "2.51%"], ["NFLX", "$810.37", "2.42%"], ["NVDA", "$147.97", "6.32%"], ["PLTR", "$59.04", "1.27%"], ["TSLA", "$340.22", "14.72%"], ["ULTA", "$384.11", "-2.29%"], ["UNH", "$617.46", "2.61%"]]], "5sheaffermalia": [109864.5, "https://www.investopedia.com/simulator/games/user-portfolio?portfolio=10445743", [["BND", "$72.69", "-2.57%"], ["BRK.B", "$467.50", "5.89%"], ["COST", "$938.55", "8.36%"], ["DJT", "$30.25", "-40.85%"], ["NVDA", "$147.97", "26.38%"], ["SO", "$88.28", "1.66%"], ["SPY", "$597.18", "7.09%"]]], "2mirilily": [110795.69, "https://www.investopedia.com/simulator/games/user-portfolio?portfolio=10447818", [["ANET", "$395.93", "11.58%"], ["GE", "$181.59", "6.25%"], ["HWKN", "$127.02", "7.38%"], ["ISRG", "$532.24", "10.19%"], ["LLY", "$815.68", "-12.49%"], ["META", "$585.01", "9.98%"], ["PANW", "$397.37", "13.96%"], ["RCL", "$232.92", "44.85%"], ["SPOT", "$414.18", "22.37%"], ["SPY", "$597.18", "6.58%"], ["UBER", "$72.14", "-2.58%"], ["VGT", "$621.85", "7.91%"]]], "6saishyamrugoobur": [110901.65, "https://www.investopedia.com/simulator/games/user-portfolio?portfolio=10449081", [["AAPL", "$225.28", "-0.44%"], ["AMZN", "$206.26", "16.71%"], ["GOOGL", "$179.53", "7.90%"], ["HD", "$406.46", "11.15%"], ["MSFT", "$420.40", "0.97%"], ["NVDA", "$148.13", "20.24%"], ["TSLA", "$339.40", "54.60%"]]], "2wuchristopher": [102568.99, "https://www.investopedia.com/simulator/games/user-portfolio?portfolio=10447839", [["AAPL", "$225.28", "0.20%"], ["AMD", "$144.21", "-4.29%"], ["DJT", "$30.34", "-31.76%"], ["GOOGL", "$179.53", "11.31%"], ["NVDA", "$148.13", "18.78%"], ["SWBI", "$13.27", "-9.60%"], ["TSM", "$190.35", "9.62%"], ["TTWO", "$178.96", "22.99%"]]], "3patilrohi": [113648.92, "https://www.investopedia.com/simulator/games/user-portfolio?portfolio=10445348", [["AAPL", "$225.28", "-3.89%"], ["AMZN", "$206.22", "17.01%"], ["META", "$585.01", "10.56%"], ["NOW", "$1,040.99", "10.83%"], ["NVDA", "$147.97", "5.61%"]]], "5garciaocran": [107614.46, "https://www.investopedia.com/simulator/games/user-portfolio?portfolio=10445746", [["AAPL", "$225.28", "0.61%"], ["BAC", "$46.20", "19.75%"], ["DIS", "$100.17", "12.60%"], ["LOAR", "$87.96", "30.78%"], ["NKE", "$76.50", "-7.57%"], ["NVDA", "$147.97", "21.48%"]]], "5jianglin": [113015.93, "https://www.investopedia.com/simulator/games/user-portfolio?portfolio=10445749", [["HYG", "$79.47", "1.30%"], ["ROKU", "$76.47", "11.27%"], ["SHOP", "$110.94", "56.53%"], ["VOO", "$548.99", "8.67%"]]], "3baradlaydaniel": [114924.52, "https://www.investopedia.com/simulator/games/user-portfolio?portfolio=10445341", [["AAPL", "$225.28", "2.11%"], ["ARDX", "$4.66", "-25.76%"], ["BNO", "$28.55", "-7.40%"], ["HCP", "$34.07", "0.32%"], ["SGC", "$17.07", "12.67%"], ["SNY", "$50.34", "-12.57%"]]], "5tingjanele": [111216.16, "https://www.investopedia.com/simulator/games/user-portfolio?portfolio=10445733", [["ADMA", "$22.06", "20.62%"], ["AMD", "$144.21", "-7.85%"], ["AVGO", "$175.99", "11.37%"], ["CRM", "$344.50", "35.22%"], ["CRWD", "$336.83", "27.47%"], ["GOOGL", "$179.53", "7.90%"], ["HD", "$406.46", "13.13%"], ["NVDA", "$148.13", "21.96%"], ["SBUX", "$98.44", "3.19%"]]], "2dersecamren": [112308.23, "https://www.investopedia.com/simulator/games/user-portfolio?portfolio=10447825", [["AAPL", "$225.25", "-4.01%"], ["ADMA", "$22.06", "42.57%"], ["AMZN", "$206.22", "9.86%"], ["APP", "$284.37", "72.95%"], ["AUR", "$5.25", "5.00%"], ["CHDN", "$140.04", "3.64%"], ["CLOV", "$3.19", "-15.85%"], ["COST", "$937.56", "4.00%"], ["CYBN", "$11.78", "30.09%"], ["DAVE", "$61.02", "45.08%"], ["DJT", "$30.25", "-18.38%"], ["EA", "$161.63", "10.43%"], ["JPM", "$239.87", "6.83%"], ["LULU", "$318.24", "8.40%"], ["NKE", "$76.50", "-5.10%"], ["OUT", "$17.59", "-3.62%"], ["SKYT", "$8.32", "-15.55%"], ["SOFI", "$13.73", "30.49%"], ["SPGI", "$505.63", "2.10%"], ["SWK", "$88.32", "-17.37%"], ["WOK", "$5.73", "-21.51%"]]], "3lustephanie": [112905.95, "https://www.investopedia.com/simulator/games/user-portfolio?portfolio=10445340", [["AMZN", "$206.26", "9.26%"], ["CAVA", "$144.52", "19.19%"], ["EA", "$161.83", "15.03%"], ["GE", "$181.59", "3.84%"], ["JPM", "$239.99", "11.47%"], ["KVUE", "$23.75", "7.77%"], ["NKE", "$76.61", "-6.60%"], ["NVDA", "$147.97", "19.35%"], ["PLTR", "$59.03", "50.19%"], ["TSLA", "$339.40", "58.83%"]]], "helllloo11": [110435.11, "https://www.investopedia.com/simulator/games/user-portfolio?portfolio=10445754", [["AMD", "$144.35", "-4.37%"], ["DOG", "$25.84", "-0.40%"], ["DRUG", "$42.78", "-7.72%"], ["PDD", "$112.71", "-12.40%"]]], "5gollamudinikhil": [105439.96, "https://www.investopedia.com/simulator/games/user-portfolio?portfolio=10445734", [["AAPL", "$225.28", "0.12%"], ["AVGO", "$175.99", "-4.04%"], ["NDAQ", "$79.76", "14.34%"], ["NFLX", "$810.37", "1.82%"], ["NKE", "$76.61", "1.67%"], ["NVDL", "$84.14", "-0.31%"], ["PEP", "$164.33", "-0.39%"], ["TMUS", "$236.89", "7.03%"], ["TSLA", "$339.40", "-1.99%"]]], "2phamjinny": [110481.2, "https://www.investopedia.com/simulator/games/user-portfolio?portfolio=10447859", [["AAPL", "$225.25", "-0.11%"], ["AMZN", "$206.22", "16.06%"], ["COST", "$937.56", "7.61%"], ["MSFT", "$420.40", "0.42%"], ["NVDA", "$147.97", "19.89%"], ["PACS", "$21.81", "-46.64%"], ["RDDT", "$127.71", "116.17%"], ["TSLA", "$340.22", "57.57%"]]], "3shihmercury": [104914.58, "https://www.investopedia.com/simulator/games/user-portfolio?portfolio=10445333", [["AMD", "$144.21", "-2.76%"], ["AVGO", "$175.99", "6.39%"], ["CRWD", "$336.83", "31.14%"], ["MSFT", "$420.40", "0.25%"], ["NVDA", "$148.13", "22.01%"], ["PLTR", "$59.03", "94.71%"], ["QQQ", "$512.73", "8.14%"]]], "3liuallen": [109197.8, "https://www.investopedia.com/simulator/games/user-portfolio?portfolio=10445351", [["AMZN", "$206.22", "9.44%"], ["CMCSA", "$44.13", "12.56%"], ["GS", "$594.85", "19.12%"], ["JPM", "$239.87", "15.49%"], ["LLY", "$815.04", "-13.90%"], ["MCD", "$300.54", "9.21%"], ["MSFT", "$420.40", "1.02%"], ["NDAQ", "$79.76", "10.45%"], ["NVDA", "$147.97", "23.20%"], ["SPGI", "$505.63", "-2.46%"], ["TKO", "$116.49", "-5.78%"], ["TSLA", "$339.40", "60.52%"], ["WMT", "$85.15", "14.40%"]]], "5mehtasuhani": [107999.26, "https://www.investopedia.com/simulator/games/user-portfolio?portfolio=10445732", [["AAPL", "$225.25", "0.61%"], ["COST", "$937.56", "5.14%"], ["CSCO", "$58.63", "18.58%"], ["LULU", "$318.24", "23.25%"], ["NVDA", "$147.97", "18.05%"], ["ORCL", "$188.25", "36.59%"], ["SBUX", "$98.44", "5.44%"], ["SPOT", "$414.48", "23.56%"]]], "2habibvandarion": [106035.73, "https://www.investopedia.com/simulator/games/user-portfolio?portfolio=10447822", [["AMD", "$144.21", "-2.72%"], ["AMZN", "$206.26", "16.54%"], ["GOOG", "$181.22", "9.34%"], ["NVDA", "$147.97", "17.70%"], ["TSM", "$189.75", "11.18%"]]], "5xieanthony": [107715.16, "https://www.investopedia.com/simulator/games/user-portfolio?portfolio=10445737", [["AAPL", "$225.28", "0.45%"], ["AMZN", "$206.22", "11.04%"], ["NVDA", "$147.97", "16.18%"], ["V", "$309.55", "9.20%"]]], "2nguyenthien": [108054.39, "https://www.investopedia.com/simulator/games/user-portfolio?portfolio=10447866", [["TT", "$409.80", "9.55%"], ["TTWO", "$178.96", "21.91%"]]], "3sudharsanshrivas": [115869.86, "https://www.investopedia.com/simulator/games/user-portfolio?portfolio=10445345", [["AAPL", "$225.28", "2.87%"], ["BRK.B", "$467.50", "4.17%"], ["PLTR", "$59.04", "72.44%"], ["VRTX", "$499.16", "1.87%"], ["VZ", "$40.28", "-2.73%"]]], "2gaudaanvi": [108645.32, "https://www.investopedia.com/simulator/games/user-portfolio?portfolio=10453457", [["AAPL", "$225.25", "-0.17%"], ["BLK", "$1,051.04", "20.88%"], ["CCJ", "$52.29", "22.60%"], ["CLSK", "$16.51", "37.24%"], ["ORCL", "$188.25", "36.67%"], ["QQQ", "$512.73", "14.22%"], ["VOO", "$549.23", "6.93%"]]], "p3_horvath_levente": [105667.69, "https://www.investopedia.com/simulator/games/user-portfolio?portfolio=10451510", [["AAPL", "$225.28", "0.12%"], ["AMZN", "$206.22", "16.24%"], ["NVDA", "$147.97", "18.66%"], ["TT", "$409.80", "1.37%"]]], "1buijason": [104855.49, "https://www.investopedia.com/simulator/games/user-portfolio?portfolio=10444534", [["ADSK", "$309.15", "6.96%"], ["COST", "$937.56", "4.25%"], ["DELL", "$137.19", "-0.68%"], ["DUOL", "$317.73", "0.22%"], ["EA", "$161.63", "12.17%"], ["ELF", "$129.44", "5.54%"], ["HD", "$406.46", "2.83%"], ["NET", "$90.58", "-6.46%"], ["NVDA", "$147.97", "4.80%"], ["UBER", "$72.08", "-7.36%"]]], "5bisharajeries": [105868.93, "https://www.investopedia.com/simulator/games/user-portfolio?portfolio=10445748", [["RIVN", "$10.61", "4.48%"]]], "1parkcaleb": [105900.94, "https://www.investopedia.com/simulator/games/user-portfolio?portfolio=10444525", [["AMD", "$144.21", "-10.61%"], ["F", "$11.04", "1.21%"], ["JPM", "$239.99", "14.20%"], ["KO", "$63.48", "-8.51%"], ["MSFT", "$420.40", "0.39%"], ["NVDA", "$148.13", "15.57%"]]], "2sepelucas": [106372.3, "https://www.investopedia.com/simulator/games/user-portfolio?portfolio=10448346", [["LB", "$70.10", "99.77%"], ["LULU", "$318.24", "15.87%"], ["NVDA", "$148.13", "17.43%"], ["SPYG", "$87.43", "9.42%"]]], "2chenkhai": [108856.68, "https://www.investopedia.com/simulator/games/user-portfolio?portfolio=10447832", [["ABNB", "$134.16", "15.99%"], ["BBWI", "$31.78", "-7.46%"], ["CMCSA", "$44.10", "10.36%"], ["COST", "$938.55", "6.86%"], ["CVS", "$53.86", "-6.93%"], ["F", "$11.06", "-0.36%"], ["INTC", "$23.99", "0.19%"], ["KSS", "$18.61", "-3.92%"], ["LULU", "$318.23", "19.18%"], ["MSI", "$494.50", "15.97%"], ["NKE", "$76.61", "-7.57%"], ["RDDT", "$127.71", "116.53%"], ["TGT", "$155.94", "14.14%"], ["UPS", "$131.16", "2.20%"]]], "5polakella": [107061.74, "https://www.investopedia.com/simulator/games/user-portfolio?portfolio=10445726", [["ASML", "$669.26", "-24.33%"], ["CRWD", "$337.26", "32.99%"], ["REGN", "$820.81", "-29.60%"]]], "5vajirkararnav": [104532.12, "https://www.investopedia.com/simulator/games/user-portfolio?portfolio=10445738", [["AAPL", "$225.25", "1.39%"], ["MSFT", "$420.40", "1.35%"], ["QQQ", "$512.73", "8.23%"], ["RACE", "$440.42", "-5.19%"]]], "kayanshah": [107964.79, "https://www.investopedia.com/simulator/games/user-portfolio?portfolio=10445751", [["ADBE", "$523.40", "-3.72%"], ["GOOG", "$181.22", "11.16%"], ["KB", "$65.20", "-1.03%"], ["META", "$585.01", "10.68%"], ["NVDA", "$148.13", "16.58%"], ["PLTR", "$59.03", "36.96%"], ["SPY", "$597.18", "8.29%"], ["UCO", "$25.20", "-14.59%"], ["WLDN", "$46.45", "8.60%"]]], "6nagpurwalafayezah": [106237.56, "https://www.investopedia.com/simulator/games/user-portfolio?portfolio=10449071", [["AAPL", "$225.28", "-3.95%"], ["HRB", "$60.95", "-9.28%"], ["MSFT", "$420.40", "-2.54%"], ["TSLA", "$339.40", "33.04%"]]], "5nguyendaphne": [106781.29, "https://www.investopedia.com/simulator/games/user-portfolio?portfolio=10445728", [["ADBE", "$523.40", "8.30%"], ["AMZN", "$206.22", "9.63%"], ["BECN", "$104.19", "8.99%"], ["DAL", "$63.11", "58.79%"], ["GOOGL", "$179.53", "9.12%"], ["LLY", "$816.74", "-2.25%"], ["MSFT", "$420.40", "1.35%"], ["NVDA", "$147.97", "7.03%"], ["QQQ", "$512.73", "3.47%"], ["RDDT", "$127.71", "37.49%"], ["SPOT", "$414.18", "10.32%"], ["SPY", "$597.08", "1.27%"], ["TQQQ", "$82.13", "15.56%"], ["TSLA", "$340.22", "38.68%"], ["TXN", "$212.74", "7.36%"]]], "1anandnikita": [105066.01, "https://www.investopedia.com/simulator/games/user-portfolio?portfolio=10444526", [["AAPL", "$225.28", "1.93%"], ["MCD", "$300.54", "11.05%"], ["NVDA", "$147.97", "29.16%"], ["ONON", "$52.80", "23.77%"], ["SBUX", "$98.68", "6.11%"], ["SPOT", "$414.18", "22.84%"], ["TMUS", "$236.89", "21.36%"]]], "1elyasiarian": [106362.64, "https://www.investopedia.com/simulator/games/user-portfolio?portfolio=10444532", [["BRK.B", "$467.50", "4.45%"], ["DIA", "$441.41", "8.21%"], ["MSFT", "$420.40", "1.74%"]]], "1mungaiayanna": [102368.23, "https://www.investopedia.com/simulator/games/user-portfolio?portfolio=10444528", [["BA", "$144.86", "-9.60%"], ["BBWI", "$31.76", "0.02%"], ["MSFT", "$420.40", "-1.98%"], ["SG", "$38.41", "-5.08%"]]], "5zhounatalie": [113260.17, "https://www.investopedia.com/simulator/games/user-portfolio?portfolio=10445725", [["AAPL", "$225.28", "1.53%"], ["AMZN", "$206.22", "10.27%"], ["BRK.B", "$467.50", "1.92%"], ["COST", "$938.55", "8.40%"], ["JPM", "$239.87", "13.21%"], ["NVDA", "$147.97", "14.20%"], ["TSLA", "$340.22", "53.67%"]]], "5lucaslloyd": [118810.54, "https://www.investopedia.com/simulator/games/user-portfolio?portfolio=10445741", [["CONL", "$61.55", "89.13%"], ["DKNG", "$42.28", "23.50%"], ["MODG", "$9.49", "-16.65%"], ["NVDL", "$84.14", "30.29%"], ["PLTR", "$59.03", "86.05%"], ["QQQ", "$512.73", "8.62%"], ["SOXL", "$31.56", "-19.67%"], ["SSO", "$96.69", "14.20%"], ["UBER", "$72.08", "-1.97%"]]], "2tavakoliariana": [104755.51, "https://www.investopedia.com/simulator/games/user-portfolio?portfolio=10447812", [["AAPL", "$225.28", "1.88%"], ["COST", "$938.55", "8.75%"], ["NFLX", "$810.37", "22.89%"], ["NVDA", "$148.13", "24.16%"], ["QQQ", "$512.73", "11.16%"], ["SMH", "$251.08", "6.76%"], ["VOO", "$549.23", "8.35%"], ["WOK", "$5.73", "-21.51%"]]], "3leesienna": [107424.16, "https://www.investopedia.com/simulator/games/user-portfolio?portfolio=10445339", [["APP", "$284.37", "1.20%"], ["AVGO", "$175.75", "0.49%"], ["COST", "$938.55", "3.72%"], ["LLY", "$816.74", "-11.75%"], ["META", "$584.80", "8.98%"], ["MSFT", "$420.40", "-3.68%"], ["NVDA", "$148.13", "27.49%"], ["SBUX", "$98.68", "5.61%"], ["SHOP", "$111.21", "58.24%"], ["TSLA", "$339.40", "-0.98%"]]], "5telikepallisharvil": [92713.86, "https://www.investopedia.com/simulator/games/user-portfolio?portfolio=10445747", [["AMD", "$144.21", "-0.90%"], ["DJT", "$30.25", "-17.62%"], ["MSFT", "$420.40", "0.14%"], ["NOC", "$531.04", "5.33%"], ["NVDA", "$147.97", "13.93%"], ["WMT", "$85.11", "12.47%"]]], "1nguyenkatie": [110055.86, "https://www.investopedia.com/simulator/games/user-portfolio?portfolio=10444527", [["AAPL", "$225.28", "-0.75%"], ["AMZN", "$206.26", "16.97%"], ["CAVA", "$144.52", "13.49%"], ["CMG", "$60.46", "4.91%"], ["COST", "$938.55", "5.54%"], ["INTC", "$23.99", "16.74%"], ["MSFT", "$420.40", "-0.83%"], ["NVDA", "$148.13", "16.28%"], ["SHOP", "$111.21", "41.10%"], ["TSLA", "$339.40", "42.22%"], ["V", "$309.55", "15.26%"]]], "2akramzaara": [104579.15, "https://www.investopedia.com/simulator/games/user-portfolio?portfolio=10447815", [["AAPL", "$225.28", "1.87%"], ["AMGN", "$319.21", "-2.30%"], ["AMZN", "$206.26", "16.71%"], ["AXP", "$289.60", "15.20%"], ["COST", "$938.55", "8.82%"], ["CSCO", "$58.63", "18.16%"], ["LLY", "$815.04", "-13.73%"], ["LULU", "$318.23", "22.04%"], ["MRCY", "$43.51", "9.82%"], ["NFLX", "$810.37", "22.60%"], ["NVDA", "$147.97", "17.91%"], ["PANW", "$397.37", "6.71%"]]], "teachermiller": [107967.71, "https://www.investopedia.com/simulator/games/user-portfolio?portfolio=10442516", [["AHR", "$26.29", "23.98%"], ["AZI", "$2.51", "-18.40%"], ["INGM", "$23.71", "-1.64%"], ["LB", "$70.10", "105.60%"], ["LOAR", "$87.96", "18.54%"], ["NNE", "$22.35", "108.84%"], ["PACS", "$21.81", "-44.53%"], ["RDDT", "$127.71", "138.71%"], ["RYDE", "$0.50", "-94.28%"], ["SEPN", "$23.15", "4.34%"], ["ULS", "$50.29", "-2.27%"], ["WOK", "$5.73", "54.33%"], ["YXT", "$2.04", "-78.06%"]]], "1phamriley": [107611.81, "https://www.investopedia.com/simulator/games/user-portfolio?portfolio=10444529", [["AAPL", "$225.28", "-1.40%"], ["AMD", "$144.21", "-8.59%"], ["AMZN", "$206.22", "16.31%"], ["ASTS", "$24.38", "-34.91%"], ["LB", "$70.05", "88.44%"], ["NFLX", "$810.37", "15.93%"], ["NVDA", "$147.97", "18.91%"], ["PAYC", "$230.01", "42.91%"], ["TSLA", "$339.40", "53.74%"]]], "3knightizabella": [103592.58, "https://www.investopedia.com/simulator/games/user-portfolio?portfolio=10445342", []], "1ngohailey": [104343.36, "https://www.investopedia.com/simulator/games/user-portfolio?portfolio=10444524", [["AAPL", "$225.28", "0.61%"], ["AMZN", "$206.22", "16.09%"], ["CSCO", "$58.68", "16.98%"], ["NFLX", "$810.37", "16.14%"], ["NVDA", "$147.97", "14.88%"], ["SBUX", "$98.68", "6.39%"]]], "1mostafavidaniel": [103234.21, "https://www.investopedia.com/simulator/games/user-portfolio?portfolio=10444521", [["AAPL", "$225.28", "0.49%"], ["ABT", "$116.86", "3.49%"], ["CAVA", "$144.52", "47.80%"], ["CMG", "$60.40", "16.10%"], ["FTNT", "$98.74", "30.50%"], ["GE", "$181.59", "7.07%"], ["LMT", "$567.36", "2.05%"], ["LWAY", "$24.12", "44.31%"], ["NICE", "$193.05", "6.48%"], ["NOC", "$531.55", "5.44%"], ["NVDA", "$148.13", "17.10%"], ["TRGP", "$194.58", "3.94%"], ["TSM", "$190.35", "9.40%"], ["ULTA", "$384.11", "-2.12%"], ["VSTS", "$13.97", "4.92%"]]], "2daosean": [103407.9, "https://www.investopedia.com/simulator/games/user-portfolio?portfolio=10447838", [["AAPL", "$225.28", "1.81%"], ["JPM", "$239.87", "16.62%"], ["NKE", "$76.61", "-1.79%"], ["NVDA", "$147.97", "15.84%"], ["SPGI", "$505.63", "2.45%"]]], "2santosshin": [112636.07, "https://www.investopedia.com/simulator/games/user-portfolio?portfolio=10447823", [["LUMN", "$9.28", "40.59%"], ["MSTR", "$340.04", "24.05%"], ["NVDA", "$147.97", "7.23%"], ["SMMT", "$21.57", "7.37%"]]], "2chobanianbella": [103978.48, "https://www.investopedia.com/simulator/games/user-portfolio?portfolio=10447819", [["AAPL", "$225.28", "0.44%"], ["AMZN", "$206.26", "16.57%"], ["COST", "$938.55", "7.24%"], ["DJT", "$30.25", "-17.67%"], ["GOOG", "$181.22", "8.60%"], ["LULU", "$318.23", "21.92%"], ["NVDA", "$147.97", "16.69%"], ["TSLA", "$339.40", "58.12%"]]], "2andersonrhys": [102961.19, "https://www.investopedia.com/simulator/games/user-portfolio?portfolio=10447820", [["AAPL", "$225.28", "0.36%"], ["CRWD", "$337.26", "27.34%"], ["LEVI", "$16.87", "-10.98%"], ["NVDA", "$148.13", "22.76%"], ["SPAI", "$2.03", "-28.52%"]]], "2urvizoefrain": [101116.87, "https://www.investopedia.com/simulator/games/user-portfolio?portfolio=10447824", [["SG", "$38.41", "-0.94%"]]], "1byakodvedika": [111636.08, "https://www.investopedia.com/simulator/games/user-portfolio?portfolio=10444522", [["NVDA", "$147.97", "21.23%"], ["SPY", "$597.18", "6.57%"], ["TQQQ", "$82.13", "13.53%"]]], "5geselina": [104076.0, "https://www.investopedia.com/simulator/games/user-portfolio?portfolio=10445731", [["NVDA", "$148.13", "15.37%"], ["QLD", "$110.13", "11.71%"], ["QQQ", "$513.20", "7.05%"], ["SPY", "$597.18", "7.65%"]]], "2hajizadehyasmin": [103165.35, "https://www.investopedia.com/simulator/games/user-portfolio?portfolio=10447821", [["AAPL", "$225.28", "-0.18%"], ["AMZN", "$206.22", "16.04%"], ["DIS", "$100.17", "14.38%"], ["NVDA", "$147.97", "16.95%"], ["RBLX", "$54.85", "38.07%"]]], "5kanglyn": [102602.31, "https://www.investopedia.com/simulator/games/user-portfolio?portfolio=10445736", [["ADBE", "$523.40", "0.29%"], ["MSFT", "$419.64", "0.82%"]]], "6mamarianrubyna": [102169.61, "https://www.investopedia.com/simulator/games/user-portfolio?portfolio=10480692", []], "2baradlayannie": [103055.82, "https://www.investopedia.com/simulator/games/user-portfolio?portfolio=10447827", [["AAPL", "$225.28", "0.30%"], ["CART", "$47.35", "27.80%"], ["CAT", "$393.25", "13.84%"], ["COST", "$938.55", "8.80%"], ["DUOL", "$317.73", "12.96%"], ["HD", "$406.46", "9.45%"], ["JNJ", "$153.09", "-3.39%"], ["NCLH", "$27.42", "19.22%"], ["PACS", "$21.81", "-46.64%"], ["RBLX", "$54.85", "28.65%"], ["ROKU", "$76.50", "11.18%"], ["WMT", "$85.11", "5.90%"]]], "2continichris": [107686.68, "https://www.investopedia.com/simulator/games/user-portfolio?portfolio=10447845", [["INTC", "$23.99", "1.99%"]]], "1valerozadela": [102835.61, "https://www.investopedia.com/simulator/games/user-portfolio?portfolio=10444523", [["AAPL", "$225.28", "1.71%"], ["LPL", "$3.41", "-13.30%"], ["NFLX", "$810.31", "19.32%"], ["NVDA", "$148.13", "19.03%"], ["SBUX", "$98.68", "6.11%"], ["SPOT", "$414.18", "22.96%"], ["V", "$309.41", "18.57%"], ["WFC", "$72.59", "31.24%"], ["WMT", "$85.11", "16.05%"]]], "2ambrizcaden": [103471.09, "https://www.investopedia.com/simulator/games/user-portfolio?portfolio=10447813", [["AAPL", "$225.28", "1.88%"], ["AMZN", "$206.26", "21.63%"], ["ANF", "$139.41", "-12.69%"], ["BRK.B", "$467.50", "0.56%"], ["COST", "$938.55", "4.00%"], ["CSCO", "$58.68", "16.34%"], ["LULU", "$318.23", "28.25%"], ["SPGI", "$505.35", "-2.50%"], ["TGT", "$156.03", "4.97%"]]], "6valsalon": [102387.05, "https://www.investopedia.com/simulator/games/user-portfolio?portfolio=10449075", [["BA", "$144.86", "-4.14%"], ["NEE", "$74.18", "-6.43%"], ["NVDA", "$148.13", "16.11%"], ["TSLA", "$340.22", "13.73%"], ["ULTA", "$384.45", "2.78%"], ["WMT", "$85.11", "14.38%"]]], "2symmonsnatalie": [101414.12, "https://www.investopedia.com/simulator/games/user-portfolio?portfolio=10453458", [["AAPL", "$225.26", "-0.47%"], ["F", "$11.06", "6.20%"], ["LULU", "$318.23", "22.63%"], ["NKE", "$76.61", "-8.38%"]]], "5yoshioka-meonskebradley": [108635.31, "https://www.investopedia.com/simulator/games/user-portfolio?portfolio=10445745", [["AAPL", "$225.28", "0.02%"], ["ASML", "$671.60", "-0.66%"], ["CRWD", "$337.26", "11.65%"], ["CSCO", "$58.68", "6.76%"], ["DIS", "$100.00", "16.20%"], ["MCD", "$300.54", "11.02%"], ["MSFT", "$420.40", "1.09%"], ["RSPA", "$53.15", "3.32%"], ["VOOG", "$364.22", "8.11%"]]], "shankmoitra": [89467.56, "https://www.investopedia.com/simulator/games/user-portfolio?portfolio=10445729", [["ADBE", "$524.76", "-2.71%"], ["AMD", "$144.21", "-8.77%"], ["LRCX", "$75.63", "-12.80%"], ["MSFT", "$420.40", "0.38%"], ["SMCI", "$22.29", "-57.95%"]]], "6claypillora": [103973.89, "https://www.investopedia.com/simulator/games/user-portfolio?portfolio=10449074", [["AAPL", "$225.28", "-0.19%"], ["AMZN", "$206.22", "14.84%"], ["COST", "$938.55", "4.56%"], ["MCD", "$300.54", "5.31%"], ["MSFT", "$419.64", "1.39%"], ["NVDA", "$148.13", "17.18%"], ["SBUX", "$98.68", "7.91%"], ["TGT", "$156.03", "3.02%"]]], "3cookmeghan": [103905.8, "https://www.investopedia.com/simulator/games/user-portfolio?portfolio=10445337", [["FI", "$214.69", "24.86%"], ["GILD", "$96.48", "22.53%"], ["HCA", "$353.85", "-9.36%"], ["LB", "$70.10", "23.74%"], ["ORCL", "$188.25", "21.03%"], ["VGT", "$622.63", "-0.18%"]]], "6sophiamovassate": [110917.4, "https://www.investopedia.com/simulator/games/user-portfolio?portfolio=10449082", [["AMZN", "$206.22", "15.82%"], ["BAC", "$46.20", "19.01%"], ["DIS", "$100.17", "10.09%"], ["NVDA", "$147.97", "-0.48%"], ["PGR", "$260.78", "7.27%"], ["RBLX", "$54.84", "31.13%"], ["SPOT", "$414.18", "20.49%"], ["YUMC", "$47.65", "42.38%"]]], "5vincentchung": [100668.13, "https://www.investopedia.com/simulator/games/user-portfolio?portfolio=10445767", [["AAPL", "$225.28", "1.94%"], ["AMD", "$144.37", "-10.08%"], ["AMZN", "$206.26", "3.65%"], ["BLK", "$1,051.04", "6.66%"], ["BX", "$179.26", "6.05%"], ["JPM", "$239.87", "7.30%"], ["META", "$585.01", "-2.37%"], ["MSFT", "$420.40", "-3.84%"], ["NFLX", "$810.31", "7.31%"], ["NVDA", "$148.13", "9.97%"], ["SPOT", "$414.18", "8.28%"]]], "5wangwei": [107530.89, "https://www.investopedia.com/simulator/games/user-portfolio?portfolio=10445759", [["AAPL", "$225.26", "0.41%"], ["ADSK", "$309.15", "13.82%"], ["AMD", "$144.37", "-15.69%"], ["AMZN", "$206.26", "8.89%"], ["CAT", "$393.27", "1.14%"], ["COST", "$938.55", "3.64%"], ["DIS", "$100.17", "9.56%"], ["DJT", "$30.34", "-43.55%"], ["DRS", "$36.48", "14.49%"], ["DUOL", "$317.73", "14.36%"], ["ENVA", "$102.94", "15.91%"], ["GOOG", "$181.22", "11.20%"], ["GOOGL", "$179.70", "7.04%"], ["INTC", "$23.99", "-1.28%"], ["JPM", "$239.87", "6.51%"], ["MA", "$530.15", "4.52%"], ["NVDA", "$148.13", "15.22%"], ["PDD", "$113.05", "-12.23%"], ["SPOT", "$414.18", "9.63%"], ["TQQQ", "$82.22", "18.76%"], ["TSLA", "$340.22", "37.90%"], ["TSM", "$190.35", "-2.01%"], ["UBER", "$72.08", "-5.49%"], ["ULTA", "$384.45", "-2.39%"], ["XOM", "$119.95", "1.30%"]]], "5ahujaalisha": [101387.29, "https://www.investopedia.com/simulator/games/user-portfolio?portfolio=10445740", [["APD", "$312.31", "-5.64%"], ["COIN", "$309.92", "-4.02%"], ["HSY", "$179.47", "4.04%"], ["KALU", "$82.68", "-0.23%"], ["LUNR", "$10.53", "9.12%"]]], "seyeong": [103259.89, "https://www.investopedia.com/simulator/games/user-portfolio?portfolio=10449138", [["AAPL", "$225.28", "0.16%"], ["ADBE", "$524.76", "0.46%"], ["AMZN", "$206.26", "14.49%"], ["MSFT", "$420.40", "1.06%"], ["TSLA", "$340.22", "54.05%"], ["V", "$309.41", "15.85%"]]], "3hinholivia": [105537.01, "https://www.investopedia.com/simulator/games/user-portfolio?portfolio=10445335", [["INTC", "$23.99", "9.73%"], ["NVDA", "$148.13", "16.05%"], ["SMPL", "$37.07", "9.99%"], ["T", "$21.95", "9.32%"], ["TGT", "$156.03", "-2.07%"], ["TSLA", "$340.22", "54.38%"]]], "5afzalzadehlaily": [104192.61, "https://www.investopedia.com/simulator/games/user-portfolio?portfolio=10445742", [["AMD", "$144.37", "-5.57%"], ["BAC", "$46.20", "7.73%"], ["BMY", "$59.65", "11.57%"], ["INTC", "$23.99", "12.56%"], ["NVDA", "$147.97", "15.96%"], ["UNH", "$617.46", "4.28%"], ["VOO", "$549.23", "3.46%"]]], "3shitomichihiro": [101099.23, "https://www.investopedia.com/simulator/games/user-portfolio?portfolio=10445344", [["AAPL", "$225.28", "-1.32%"], ["AFB", "$11.33", "-0.87%"], ["AVGO", "$175.99", "11.42%"], ["DELL", "$137.19", "28.09%"], ["META", "$584.80", "10.85%"], ["MSFT", "$419.64", "-0.12%"], ["NVDA", "$148.13", "21.57%"], ["VZ", "$40.24", "-1.63%"]]], "3liuemily": [101358.82, "https://www.investopedia.com/simulator/games/user-portfolio?portfolio=10445347", [["DIA", "$441.41", "8.02%"], ["QQQ", "$512.73", "7.07%"], ["QQQM", "$211.23", "7.21%"]]], "3yueleanor": [100421.69, "https://www.investopedia.com/simulator/games/user-portfolio?portfolio=10445336", [["ABNB", "$134.30", "13.17%"], ["GIS", "$64.52", "-9.73%"], ["GOOG", "$181.22", "8.30%"], ["NVDA", "$148.13", "15.93%"], ["UBER", "$72.08", "-1.81%"]]], "5qinsophia": [100876.27, "https://www.investopedia.com/simulator/games/user-portfolio?portfolio=10445750", [["AMD", "$144.37", "-6.32%"], ["ASML", "$669.26", "-24.60%"], ["CRWD", "$337.26", "29.11%"], ["GOOG", "$181.22", "10.36%"], ["MSFT", "$419.64", "1.17%"], ["NVDA", "$148.13", "24.97%"]]], "6faureian": [102173.99, "https://www.investopedia.com/simulator/games/user-portfolio?portfolio=10449069", [["AAPL", "$225.28", "0.61%"], ["AMZN", "$206.26", "3.66%"], ["DIS", "$100.17", "10.89%"], ["F", "$11.06", "6.15%"], ["LMT", "$567.36", "0.17%"], ["NOC", "$531.04", "0.76%"], ["NVDA", "$148.13", "17.92%"], ["SHEL", "$65.04", "-5.51%"]]], "5kimben": [100468.9, "https://www.investopedia.com/simulator/games/user-portfolio?portfolio=10445753", []], "1prasadanika": [102544.93, "https://www.investopedia.com/simulator/games/user-portfolio?portfolio=10444536", [["CDNS", "$298.43", "8.39%"], ["COST", "$938.55", "6.53%"], ["GOOGL", "$179.53", "8.20%"], ["LUV", "$31.78", "16.93%"], ["MSFT", "$420.40", "-0.63%"], ["RIOT", "$13.90", "71.29%"]]], "3liemma": [102531.85, "https://www.investopedia.com/simulator/games/user-portfolio?portfolio=10445331", []], "1raimondiluke": [96435.83, "https://www.investopedia.com/simulator/games/user-portfolio?portfolio=10444533", [["ADSK", "$309.62", "14.05%"], ["DUOL", "$318.54", "12.37%"], ["RKLB", "$14.65", "1.07%"], ["SPOT", "$414.18", "9.31%"], ["TMUS", "$236.89", "16.43%"], ["WMT", "$85.11", "9.93%"]]], "5smithmarco": [101352.75, "https://www.investopedia.com/simulator/games/user-portfolio?portfolio=10445744", [["NVDA", "$148.13", "16.35%"], ["ORCL", "$188.25", "27.32%"], ["UBER", "$72.08", "-3.61%"], ["UNP", "$239.86", "-4.29%"], ["XOM", "$120.12", "3.27%"]]], "2neubertsophia": [100759.16, "https://www.investopedia.com/simulator/games/user-portfolio?portfolio=10447830", [["AAPL", "$225.28", "-3.75%"], ["ANET", "$396.00", "14.45%"], ["GE", "$181.79", "3.42%"], ["LULU", "$318.23", "21.14%"], ["PGR", "$260.78", "8.64%"]]], "5shihcalista": [47748.77, "https://www.investopedia.com/simulator/games/user-portfolio?portfolio=10452002", [["SMCI", "$22.39", "-48.43%"]]], "2whitecaden": [102321.63, "https://www.investopedia.com/simulator/games/user-portfolio?portfolio=10447826", [["ADBE", "$523.40", "-1.24%"], ["CMG", "$60.40", "7.01%"], ["DKS", "$200.22", "-7.56%"], ["LLY", "$815.04", "-2.52%"], ["NBIX", "$126.89", "4.17%"], ["RIVN", "$10.61", "-9.44%"]]], "6choierica": [100134.76, "https://www.investopedia.com/simulator/games/user-portfolio?portfolio=10449070", [["AMZN", "$206.26", "16.11%"], ["JNJ", "$152.93", "-3.99%"], ["MCD", "$300.54", "3.90%"], ["MSFT", "$420.40", "0.34%"], ["NVDA", "$148.13", "19.19%"]]], "6cardenasdayanara": [105113.41, "https://www.investopedia.com/simulator/games/user-portfolio?portfolio=10449076", [["AFRM", "$55.48", "41.86%"], ["BRK.B", "$467.30", "1.33%"], ["CRWD", "$337.26", "25.00%"], ["NVDA", "$148.13", "24.73%"], ["TSLA", "$340.22", "65.94%"]]], "6lopesdebritorayane": [100306.13, "https://www.investopedia.com/simulator/games/user-portfolio?portfolio=10449084", [["AAPL", "$225.28", "-0.19%"], ["AMZN", "$206.26", "16.11%"], ["DIS", "$100.17", "9.56%"], ["NKE", "$76.46", "-8.13%"], ["ULTA", "$384.45", "0.51%"]]], "5davoudibrandon": [99863.65, "https://www.investopedia.com/simulator/games/user-portfolio?portfolio=10445730", []], "2eberhartsavannah": [99933.68, "https://www.investopedia.com/simulator/games/user-portfolio?portfolio=10447853", [["MSFT", "$419.64", "-3.84%"], ["WMT", "$85.11", "3.01%"]]], "2quachisis": [100980.13, "https://www.investopedia.com/simulator/games/user-portfolio?portfolio=10447816", [["AAPL", "$225.28", "-0.39%"], ["AMD", "$144.37", "-7.31%"], ["COST", "$938.55", "6.48%"], ["HD", "$406.46", "4.55%"], ["RBLX", "$54.84", "25.43%"], ["TSLA", "$340.22", "32.89%"]]], "6luosicheng": [104270.42, "https://www.investopedia.com/simulator/games/user-portfolio?portfolio=10449077", [["AAPL", "$225.28", "-3.45%"], ["COST", "$938.55", "4.89%"], ["NVDA", "$148.13", "14.32%"], ["WOK", "$5.73", "-25.39%"]]], "3windsorlyla": [100855.98, "https://www.investopedia.com/simulator/games/user-portfolio?portfolio=10445346", [["ASTS", "$24.39", "-23.32%"], ["CMG", "$60.40", "17.00%"], ["GOOG", "$181.22", "12.18%"], ["TSLA", "$340.22", "54.93%"], ["UBS", "$31.97", "3.90%"], ["VSCO", "$36.05", "55.92%"]]], "2freyolivia": [92738.77, "https://www.investopedia.com/simulator/games/user-portfolio?portfolio=10447828", [["AAPL", "$225.26", "-2.71%"], ["AMAT", "$186.92", "-9.70%"], ["LLY", "$815.04", "-11.43%"], ["LULU", "$318.23", "10.88%"], ["NVDA", "$148.13", "17.12%"], ["RKLB", "$14.65", "115.66%"]]], "3koushikpreksha": [105180.4, "https://www.investopedia.com/simulator/games/user-portfolio?portfolio=10445330", [["BAC", "$46.14", "14.12%"], ["COST", "$938.55", "3.61%"], ["DASH", "$175.48", "21.69%"], ["EA", "$161.63", "8.83%"], ["ISRG", "$534.24", "10.36%"], ["RDNT", "$82.77", "21.00%"], ["SHW", "$386.82", "3.22%"], ["SMMT", "$21.72", "-12.75%"], ["SMR", "$22.98", "4.79%"], ["TEM", "$72.34", "6.43%"], ["TMUS", "$236.89", "9.60%"]]], "3bhatiaarnay": [106608.81, "https://www.investopedia.com/simulator/games/user-portfolio?portfolio=10445352", [["ASTS", "$24.39", "11.35%"], ["QQQ", "$512.73", "10.62%"]]], "ufatalo": [97366.87, "https://www.investopedia.com/simulator/games/user-portfolio?portfolio=10449072", [["AAPL", "$225.26", "0.09%"], ["AMZN", "$206.26", "17.95%"], ["GOOG", "$181.39", "11.72%"], ["NVDA", "$148.13", "24.73%"], ["OSTX", "$2.71", "-33.90%"]]], "6chaocaleb": [98995.73, "https://www.investopedia.com/simulator/games/user-portfolio?portfolio=10449078", [["DUOL", "$318.54", "-1.27%"]]], "2alexialee": [98335.97, "https://www.investopedia.com/simulator/games/user-portfolio?portfolio=10447834", [["COST", "$938.55", "-1.10%"], ["TSLA", "$340.22", "6.79%"]]], "2bumanlagjacob": [94211.34, "https://www.investopedia.com/simulator/games/user-portfolio?portfolio=10447811", [["IRM", "$116.29", "-4.48%"], ["TT", "$409.80", "3.26%"], ["WAB", "$199.65", "5.04%"]]], "2greenesal": [98536.27, "https://www.investopedia.com/simulator/games/user-portfolio?portfolio=10447817", [["AAPL", "$225.28", "0.01%"], ["AVGO", "$175.99", "2.23%"], ["AXP", "$289.60", "7.03%"], ["COST", "$938.55", "4.48%"], ["DUOL", "$318.54", "11.30%"], ["HD", "$406.46", "0.92%"], ["NVDA", "$148.13", "8.43%"], ["PLTR", "$59.04", "35.01%"], ["RDDT", "$127.71", "9.44%"], ["WMT", "$85.11", "5.93%"]]], "3vobryant": [89397.81, "https://www.investopedia.com/simulator/games/user-portfolio?portfolio=10445338", [["FNGD", "$16.50", "-19.11%"], ["SERV", "$8.69", "-18.40%"]]], "6slacklucas": [82006.88, "https://www.investopedia.com/simulator/games/user-portfolio?portfolio=10449067", [["AMZN", "$206.26", "10.02%"], ["DJT", "$30.34", "-8.52%"], ["NVDA", "$148.13", "8.42%"], ["WMT", "$85.11", "6.80%"]]], "3yanjoshua": [77327.85, "https://www.investopedia.com/simulator/games/user-portfolio?portfolio=10445343", [["AMDL", "$11.21", "-19.15%"], ["BABA", "$91.94", "-10.15%"]]], "5hsutitus": [96632.34, "https://www.investopedia.com/simulator/games/user-portfolio?portfolio=10445727", [["AMZN", "$206.28", "2.18%"], ["COST", "$937.23", "6.05%"], ["DUOL", "$318.54", "9.97%"], ["GOOGL", "$179.70", "10.99%"], ["KR", "$59.82", "12.59%"], ["RDDT", "$127.71", "116.31%"], ["SPOT", "$414.18", "11.78%"]]], "6ishiguronobuhisa": [93907.63, "https://www.investopedia.com/simulator/games/user-portfolio?portfolio=10449068", [["AAPL", "$225.26", "1.63%"], ["SPGI", "$505.35", "-1.23%"]]], "3goldsmithsusannah": [71827.58, "https://www.investopedia.com/simulator/games/user-portfolio?portfolio=10445332", [["ASML", "$671.60", "-7.94%"], ["NCNA", "$1.59", "-47.91%"], ["SMCI", "$22.39", "-22.33%"]]], "3linandrew": [58196.58, "https://www.investopedia.com/simulator/games/user-portfolio?portfolio=10445354", [["ABIO", "$0.00", "-100.00%"], ["AMZN", "$206.26", "3.46%"]]], "1paliwalpinak": [117796.73, "https://www.investopedia.com/simulator/games/user-portfolio?portfolio=10444530", [["BITU", "$45.20", "0.65%"]]], "all_in_tqqq": [107386.51, "https://www.investopedia.com/simulator/games/user-portfolio?portfolio=10701005", [["TQQQ", "$82.22", "7.29%"]]]}
