{"teachermiller": [110859.82, "https://www.investopedia.com/simulator/games/user-portfolio?portfolio=10442516", [["AHR", "$7,197.50", "35.77%"], ["AZI", "$2,806.70", "-46.22%"], ["INGM", "$4,392.00", "-8.92%"], ["IZTC", "$5,295.50", "14.10%"], ["LB", "$11,082.00", "116.69%"], ["LOAR", "$6,357.05", "22.39%"], ["NNE", "$11,817.40", "140.05%"], ["PACS", "$4,067.50", "-58.62%"], ["RDDT", "$12,588.75", "161.45%"], ["RYDE", "$252.30", "-95.22%"], ["SEPN", "$5,215.50", "4.46%"], ["ULS", "$5,504.00", "6.96%"], ["WOK", "$7,501.00", "55.41%"], ["WRD", "$5,709.00", "5.78%"], ["YXT", "$1,562.00", "-69.46%"]]], "1mostafavidaniel": [102386.45, "https://www.investopedia.com/simulator/games/user-portfolio?portfolio=10444521", [["AAPL", "$4,149.00", "2.81%"], ["ABT", "$2,364.40", "4.69%"], ["CAVA", "$2,824.80", "44.45%"], ["CMG", "$2,425.61", "19.56%"], ["FTNT", "$1,411.05", "24.33%"], ["GE", "$1,618.65", "5.92%"], ["LMT", "$5,178.30", "-6.86%"], ["LWAY", "$1,451.40", "44.76%"], ["NICE", "$1,459.92", "0.66%"], ["NOC", "$2,402.68", "-4.58%"], ["NVDA", "$2,459.88", "8.15%"], ["TRGP", "$5,020.63", "7.28%"], ["TSM", "$1,845.90", "6.09%"], ["ULTA", "$3,638.15", "-7.29%"], ["VSTS", "$1,638.50", "23.10%"]]], "1byakodvedika": [106881.75, "https://www.investopedia.com/simulator/games/user-portfolio?portfolio=10444522", [["NVDA", "$1,366.60", "11.96%"], ["SPY", "$5,972.40", "6.58%"], ["TQQQ", "$98,721.00", "8.31%"]]], "1valerozadela": [102962.58, "https://www.investopedia.com/simulator/games/user-portfolio?portfolio=10444523", [["AAPL", "$1,844.00", "4.06%"], ["NFLX", "$1,732.21", "27.52%"], ["NVDA", "$1,369.59", "-4.83%"], ["SBUX", "$1,741.82", "3.44%"], ["SPOT", "$7,071.45", "11.07%"], ["TSLA", "$1,039.62", "2.75%"], ["V", "$1,557.30", "19.30%"], ["WMT", "$1,249.92", "21.68%"]]], "1ngohailey": [104069.05, "https://www.investopedia.com/simulator/games/user-portfolio?portfolio=10444524", [["AAPL", "$5,301.50", "2.94%"], ["AMZN", "$5,835.09", "13.25%"], ["CSCO", "$5,858.00", "16.89%"], ["NFLX", "$6,928.84", "24.12%"], ["NVDA", "$10,682.79", "6.33%"], ["SBUX", "$5,532.84", "10.74%"]]], "1parkcaleb": [105257.26, "https://www.investopedia.com/simulator/games/user-portfolio?portfolio=10444525", [["ADBE", "$10,340.00", "-1.35%"], ["AMD", "$21,126.75", "-12.69%"], ["INTC", "$5,016.34", "-1.10%"], ["JPM", "$37,570.50", "19.25%"], ["KO", "$4,482.14", "-7.75%"], ["NVDA", "$20,499.00", "6.73%"]]], "1anandnikita": [105986.43, "https://www.investopedia.com/simulator/games/user-portfolio?portfolio=10444526", [["AAPL", "$5,301.50", "4.29%"], ["MCD", "$5,320.62", "9.22%"], ["NVDA", "$6,013.04", "19.29%"], ["ONON", "$2,321.20", "36.03%"], ["SBUX", "$5,532.84", "10.45%"], ["SPOT", "$7,100.40", "40.39%"], ["TMUS", "$6,244.16", "22.94%"]]], "1nguyenkatie": [110319.66, "https://www.investopedia.com/simulator/games/user-portfolio?portfolio=10444527", [["AAPL", "$11,525.00", "1.55%"], ["AMZN", "$6,033.60", "14.05%"], ["CAVA", "$4,227.45", "10.66%"], ["CMG", "$621.95", "7.93%"], ["COST", "$33,426.40", "7.51%"], ["INTC", "$1,254.09", "22.06%"], ["MSFT", "$12,497.10", "-1.74%"], ["NVDA", "$8,199.60", "7.27%"], ["SHOP", "$5,585.00", "42.07%"], ["TSLA", "$13,861.60", "45.22%"], ["V", "$3,114.70", "15.98%"]]], "1mungaiayanna": [107085.07, "https://www.investopedia.com/simulator/games/user-portfolio?portfolio=10444528", [["BA", "$15,318.00", "-4.41%"], ["DELL", "$14,331.50", "-0.80%"], ["MSFT", "$20,833.50", "-2.85%"]]], "1phamriley": [107684.99, "https://www.investopedia.com/simulator/games/user-portfolio?portfolio=10444529", [["AAPL", "$3,457.50", "0.89%"], ["AMD", "$3,525.00", "-10.63%"], ["AMZN", "$5,633.88", "13.47%"], ["ASTS", "$725.40", "-35.47%"], ["LB", "$1,994.76", "98.60%"], ["NFLX", "$4,330.53", "23.90%"], ["NVDA", "$6,833.00", "9.70%"], ["PAYC", "$5,889.50", "46.49%"], ["TSLA", "$10,396.20", "56.98%"]]], "1paliwalpinak": [129981.44, "https://www.investopedia.com/simulator/games/user-portfolio?portfolio=10444530", [["MANU", "$1,027.80", "-1.66%"], ["NVDL", "$128,908.59", "-11.51%"]]], "1elyasiarian": [107384.47, "https://www.investopedia.com/simulator/games/user-portfolio?portfolio=10444532", [["BRK.B", "$21,513.15", "6.81%"], ["DIA", "$44,732.01", "9.66%"], ["MSFT", "$5,000.04", "0.84%"]]], "1raimondiluke": [123477.74, "https://www.investopedia.com/simulator/games/user-portfolio?portfolio=10444533", [["ADSK", "$5,103.04", "17.48%"], ["DUOL", "$2,403.70", "21.45%"], ["TMUS", "$4,806.20", "18.11%"], ["WMT", "$4,464.00", "15.31%"]]], "1buijason": [106600.04, "https://www.investopedia.com/simulator/games/user-portfolio?portfolio=10444534", [["ADSK", "$9,568.20", "10.35%"], ["COST", "$19,096.00", "6.17%"], ["DELL", "$4,299.45", "3.75%"], ["DUOL", "$4,120.62", "8.31%"], ["EA", "$16,913.63", "11.25%"], ["HD", "$5,561.40", "7.47%"], ["INTC", "$5,016.34", "3.99%"], ["NET", "$3,108.60", "7.01%"], ["NVDA", "$6,833.00", "-3.21%"], ["PLTR", "$19,828.53", "5.11%"], ["SPOT", "$3,771.44", "13.93%"], ["WMT", "$7,142.40", "4.41%"]]], "1prasadanika": [102193.61, "https://www.investopedia.com/simulator/games/user-portfolio?portfolio=10444536", [["CDNS", "$3,113.00", "13.06%"], ["COST", "$2,864.40", "8.38%"], ["GOOGL", "$3,352.40", "1.02%"], ["LUV", "$6,479.00", "19.21%"], ["MSFT", "$3,750.03", "-1.51%"], ["RIOT", "$2,539.95", "49.04%"]]], "3tomaszewskiadrian": [124219.43, "https://www.investopedia.com/simulator/games/user-portfolio?portfolio=10445328", [["AMD", "$21,126.75", "-14.22%"], ["ARM", "$14,827.53", "-3.27%"], ["ASML", "$20,467.95", "-4.04%"], ["RKLB", "$24,031.80", "113.90%"]]], "3koushikpreksha": [106109.17, "https://www.investopedia.com/simulator/games/user-portfolio?portfolio=10445330", [["BAC", "$9,534.00", "17.91%"], ["DASH", "$8,841.25", "22.62%"], ["EA", "$3,285.90", "10.63%"], ["ISRG", "$13,427.75", "10.96%"], ["RDNT", "$4,897.80", "19.33%"], ["SHW", "$19,965.25", "6.56%"], ["SMMT", "$194.51", "-21.85%"], ["TMUS", "$9,612.40", "11.10%"]]], "3liemma": [109259.41, "https://www.investopedia.com/simulator/games/user-portfolio?portfolio=10445331", []], "3goldsmithsusannah": [72564.9, "https://www.investopedia.com/simulator/games/user-portfolio?portfolio=10445332", []], "3shihmercury": [102027.14, "https://www.investopedia.com/simulator/games/user-portfolio?portfolio=10445333", [["AMD", "$23,547.00", "-4.92%"], ["AVGO", "$23,178.66", "-1.32%"], ["CRWD", "$3,624.35", "40.93%"], ["MSFT", "$20,828.50", "-0.67%"], ["NVDA", "$4,382.68", "12.93%"], ["PLTR", "$1,026.72", "111.65%"], ["QQQ", "$25,311.50", "6.77%"]]], "miatarabichi": [145179.12, "https://www.investopedia.com/simulator/games/user-portfolio?portfolio=10445334", [["AMZN", "$6,033.60", "7.06%"], ["AVGO", "$8,161.50", "-1.11%"], ["HOOD", "$19,113.80", "58.94%"], ["MSTR", "$62,088.49", "127.50%"], ["NVDA", "$22,002.26", "9.68%"], ["PLTR", "$9,625.50", "73.53%"]]], "3hinholivia": [103735.81, "https://www.investopedia.com/simulator/games/user-portfolio?portfolio=10445335", [["INTC", "$2,257.35", "14.73%"], ["NVDA", "$2,054.38", "7.30%"], ["SMPL", "$2,356.46", "18.51%"], ["T", "$1,735.50", "15.28%"], ["TGT", "$12,495.39", "-17.44%"], ["TSLA", "$18,005.52", "57.12%"]]], "3yueleanor": [100158.81, "https://www.investopedia.com/simulator/games/user-portfolio?portfolio=10445336", [["ABNB", "$2,783.20", "17.27%"], ["GIS", "$5,894.55", "-8.46%"], ["GOOG", "$1,693.10", "1.18%"], ["NVDA", "$4,783.10", "7.07%"], ["UBER", "$4,388.40", "-0.44%"]]], "3cookmeghan": [103649.52, "https://www.investopedia.com/simulator/games/user-portfolio?portfolio=10445337", [["FI", "$6,644.10", "28.81%"], ["GILD", "$5,852.28", "14.34%"], ["HCA", "$4,878.00", "-16.70%"], ["LB", "$7,388.00", "30.41%"], ["ORCL", "$6,621.40", "21.63%"], ["VGT", "$6,204.45", "-0.53%"]]], "3vobryant": [100703.91, "https://www.investopedia.com/simulator/games/user-portfolio?portfolio=10445338", [["FNGD", "$29,726.90", "-5.59%"], ["SERV", "$4,332.50", "-18.64%"]]], "3leesienna": [106685.48, "https://www.investopedia.com/simulator/games/user-portfolio?portfolio=10445339", [["APP", "$9,634.50", "14.29%"], ["AVGO", "$8,161.50", "-6.80%"], ["COST", "$5,728.80", "5.52%"], ["LLY", "$3,750.90", "-18.78%"], ["META", "$5,606.33", "4.44%"], ["MSFT", "$20,833.50", "-4.53%"], ["NVDA", "$15,032.60", "9.46%"], ["SBUX", "$5,111.50", "9.68%"], ["SHOP", "$14,521.00", "58.94%"], ["TSLA", "$6,925.20", "1.03%"]]], "3lustephanie": [113285.46, "https://www.investopedia.com/simulator/games/user-portfolio?portfolio=10445340", [["AMZN", "$6,838.08", "6.56%"], ["CAVA", "$7,045.75", "16.02%"], ["EA", "$1,313.68", "16.87%"], ["GE", "$2,697.75", "2.85%"], ["JPM", "$3,506.58", "16.34%"], ["KVUE", "$1,687.70", "9.33%"], ["NKE", "$3,166.40", "-3.50%"], ["NVDA", "$12,299.40", "10.23%"], ["PLTR", "$31,764.15", "44.99%"], ["TSLA", "$41,551.20", "4.77%"]]], "3baradlaydaniel": [114753.69, "https://www.investopedia.com/simulator/games/user-portfolio?portfolio=10445341", [["AAPL", "$5,762.50", "4.49%"], ["ARDX", "$3,997.50", "-14.99%"], ["BNO", "$2,905.00", "-5.77%"], ["HCP", "$15,395.14", "-0.13%"], ["SGC", "$12,693.75", "11.72%"], ["SGMO", "$1,895.00", "-22.81%"], ["SNY", "$3,385.90", "-15.96%"]]], "3knightizabella": [107159.59, "https://www.investopedia.com/simulator/games/user-portfolio?portfolio=10445342", [["TQQQ", "$15,687.98", "3.27%"]]], "3yanjoshua": [73759.88, "https://www.investopedia.com/simulator/games/user-portfolio?portfolio=10445343", [["AMDL", "$63,926.20", "-22.90%"]]], "3shitomichihiro": [100551.2, "https://www.investopedia.com/simulator/games/user-portfolio?portfolio=10445344", [["AAPL", "$2,996.50", "0.98%"], ["AFB", "$113.10", "-1.05%"], ["AVGO", "$1,634.65", "3.63%"], ["DELL", "$716.58", "34.01%"], ["META", "$2,803.17", "6.27%"], ["MSFT", "$2,082.85", "-0.86%"], ["NVDA", "$4,793.56", "12.41%"], ["VZ", "$219.95", "7.54%"]]], "3sudharsanshrivas": [116189.19, "https://www.investopedia.com/simulator/games/user-portfolio?portfolio=10445345", [["VRTX", "$23,059.00", "-5.88%"], ["VZ", "$8,794.48", "6.29%"]]], "3windsorlyla": [100281.22, "https://www.investopedia.com/simulator/games/user-portfolio?portfolio=10445346", [["GOOG", "$5,079.30", "4.80%"], ["MCD", "$29,528.50", "0.05%"], ["UBS", "$1,125.08", "4.47%"]]], "3liuemily": [101298.37, "https://www.investopedia.com/simulator/games/user-portfolio?portfolio=10445347", [["DIA", "$5,367.84", "9.47%"], ["QQQ", "$5,062.30", "5.72%"], ["QQQM", "$4,582.60", "5.72%"]]], "3patilrohi": [112784.0, "https://www.investopedia.com/simulator/games/user-portfolio?portfolio=10445348", [["AMZN", "$19,106.40", "14.12%"], ["META", "$5,607.90", "6.03%"], ["NOW", "$68,534.70", "12.26%"], ["NVDA", "$13,695.89", "-2.25%"]]], "3awyonglinus": [103865.73, "https://www.investopedia.com/simulator/games/user-portfolio?portfolio=10445349", [["AMZN", "$102,617.10", "1.75%"]]], "3jubertcolin": [118101.1, "https://www.investopedia.com/simulator/games/user-portfolio?portfolio=10445350", [["ABNB", "$6,262.20", "13.16%"], ["ADBE", "$7,754.55", "-2.65%"], ["AMD", "$4,230.00", "-14.80%"], ["ANF", "$4,724.70", "-5.30%"], ["APDN", "$342.86", "-93.02%"], ["ASML", "$15,009.83", "-2.70%"], ["ASTS", "$4,466.83", "-13.36%"], ["BAC", "$238.43", "24.29%"], ["BIDU", "$1,408.20", "-4.18%"], ["CMG", "$2,423.66", "14.81%"], ["DUOL", "$6,863.00", "35.48%"], ["GLD", "$6,547.77", "-4.22%"], ["GOOG", "$6,775.20", "7.35%"], ["LLY", "$4,506.27", "-20.50%"], ["LMT", "$2,591.25", "-7.19%"], ["META", "$5,045.70", "5.47%"], ["NVDA", "$10,819.75", "15.61%"], ["QQQ", "$6,580.99", "4.22%"], ["RDDT", "$9,791.25", "25.33%"], ["SNY", "$4,208.19", "-15.96%"], ["WDC", "$1,116.00", "13.45%"]]], "3liuallen": [108879.75, "https://www.investopedia.com/simulator/games/user-portfolio?portfolio=10445351", [["AMZN", "$4,022.40", "6.73%"], ["CMCSA", "$5,502.28", "10.58%"], ["GS", "$3,625.53", "21.00%"], ["JPM", "$9,517.86", "20.54%"], ["LLY", "$5,251.26", "-20.75%"], ["MCD", "$2,952.85", "7.30%"], ["MSFT", "$9,583.41", "0.12%"], ["NDAQ", "$5,615.91", "12.70%"], ["NVDA", "$13,695.89", "14.03%"], ["SPGI", "$2,592.15", "0.01%"], ["TKO", "$4,775.75", "10.06%"], ["TSLA", "$7,963.98", "63.77%"], ["WMT", "$2,856.96", "19.95%"]]], "3bhatiaarnay": [112581.55, "https://www.investopedia.com/simulator/games/user-portfolio?portfolio=10445352", [["BITO", "$27,944.40", "-3.44%"], ["QQQ", "$25,300.00", "9.17%"], ["WMT", "$30,623.04", "4.71%"]]], "3linandrew": [56741.6, "https://www.investopedia.com/simulator/games/user-portfolio?portfolio=10445354", [["ABIO", "$0.00", "-100.00%"], ["AMZN", "$56,715.84", "0.89%"]]], "3bergantaro": [116624.22, "https://www.investopedia.com/simulator/games/user-portfolio?portfolio=10445355", []], "5zhounatalie": [113105.32, "https://www.investopedia.com/simulator/games/user-portfolio?portfolio=10445725", [["AAPL", "$9,209.20", "3.77%"], ["AMZN", "$8,044.80", "7.52%"], ["BRK.B", "$23,916.00", "4.28%"], ["COST", "$9,548.00", "10.40%"], ["JPM", "$2,504.70", "18.22%"], ["NVDA", "$20,499.00", "5.47%"], ["TSLA", "$34,626.00", "56.40%"]]], "5polakella": [107483.94, "https://www.investopedia.com/simulator/games/user-portfolio?portfolio=10445726", [["ASML", "$11,598.51", "-23.13%"], ["REGN", "$10,484.39", "-35.77%"]]], "5hsutitus": [98462.48, "https://www.investopedia.com/simulator/games/user-portfolio?portfolio=10445727", [["AMZN", "$20,112.00", "-0.36%"], ["GOOGL", "$4,190.50", "3.53%"], ["KHC", "$8,048.75", "3.32%"], ["KR", "$15,131.25", "7.07%"], ["TSN", "$15,935.00", "-0.58%"]]], "5nguyendaphne": [106939.49, "https://www.investopedia.com/simulator/games/user-portfolio?portfolio=10445728", [["ADBE", "$7,754.55", "6.97%"], ["AMZN", "$3,016.80", "6.92%"], ["DAL", "$1,940.10", "62.73%"], ["GOOGL", "$4,190.50", "1.88%"], ["MSFT", "$5,416.71", "0.45%"], ["NVDA", "$5,478.36", "-0.93%"], ["QQQ", "$15,186.90", "2.07%"], ["RDDT", "$5,595.00", "50.59%"], ["SPOT", "$14,200.80", "26.09%"], ["SPY", "$7,764.12", "1.28%"], ["TQQQ", "$6,275.19", "10.37%"], ["TSLA", "$6,930.80", "41.60%"], ["TXN", "$8,109.60", "2.31%"]]], "shankmoitra": [98107.19, "https://www.investopedia.com/simulator/games/user-portfolio?portfolio=10445729", [["ADBE", "$6,720.61", "-4.15%"], ["AMD", "$18,330.00", "-10.80%"], ["LRCX", "$7,331.50", "-15.46%"], ["MSFT", "$8,333.40", "-0.51%"], ["NVDA", "$22,050.38", "-6.15%"], ["SMCI", "$35,187.98", "-5.19%"]]], "5davoudibrandon": [99863.65, "https://www.investopedia.com/simulator/games/user-portfolio?portfolio=10445730", []], "5geselina": [103044.29, "https://www.investopedia.com/simulator/games/user-portfolio?portfolio=10445731", [["NVDA", "$5,204.44", "6.67%"], ["QLD", "$10,794.88", "8.52%"], ["QQQ", "$20,755.43", "5.69%"], ["SPY", "$10,750.32", "7.66%"]]], "5mehtasuhani": [109377.43, "https://www.investopedia.com/simulator/games/user-portfolio?portfolio=10445732", [["AAPL", "$5,755.75", "2.82%"], ["COST", "$9,548.00", "6.96%"], ["CSCO", "$11,694.00", "18.26%"], ["LULU", "$6,560.80", "27.05%"], ["NVDA", "$6,163.15", "9.27%"], ["ORCL", "$9,457.25", "37.24%"], ["SBUX", "$5,111.50", "9.51%"], ["SPOT", "$9,428.60", "40.64%"]]], "5tingjanele": [110304.34, "https://www.investopedia.com/simulator/games/user-portfolio?portfolio=10445733", [["ADMA", "$5,877.92", "18.18%"], ["AMD", "$9,024.00", "-9.90%"], ["AVGO", "$8,161.50", "3.30%"], ["CRM", "$6,816.40", "33.45%"], ["CRWD", "$18,136.75", "37.10%"], ["GOOGL", "$5,028.60", "0.75%"], ["HD", "$5,987.17", "19.02%"], ["NVDA", "$17,765.80", "12.64%"], ["SBUX", "$5,418.19", "7.17%"], ["WMT", "$4,464.00", "3.54%"]]], "5gollamudinikhil": [103894.1, "https://www.investopedia.com/simulator/games/user-portfolio?portfolio=10445734", [["AVGO", "$21,250.45", "-3.46%"], ["NDAQ", "$6,755.37", "16.86%"], ["RACE", "$15,277.50", "0.04%"], ["SHW", "$5,989.20", "1.86%"], ["TSLA", "$34,626.00", "-3.85%"], ["TTD", "$4,905.33", "-1.83%"]]], "5nguyenethan": [114904.55, "https://www.investopedia.com/simulator/games/user-portfolio?portfolio=10445735", [["MANU", "$17.13", "-0.75%"], ["NVDA", "$114,497.64", "-2.69%"], ["PZZA", "$49.93", "-15.39%"]]], "5kanglyn": [102474.8, "https://www.investopedia.com/simulator/games/user-portfolio?portfolio=10445736", [["ADBE", "$8,788.49", "-0.94%"], ["MSFT", "$2,083.35", "-0.07%"]]], "5xieanthony": [103683.61, "https://www.investopedia.com/simulator/games/user-portfolio?portfolio=10445737", [["AAPL", "$11,511.50", "2.66%"], ["AMZN", "$24,134.40", "8.27%"], ["NVDA", "$52,044.38", "-0.99%"], ["V", "$15,573.00", "9.88%"]]], "5vajirkararnav": [103431.53, "https://www.investopedia.com/simulator/games/user-portfolio?portfolio=10445738", []], "5wangkyan": [113576.46, "https://www.investopedia.com/simulator/games/user-portfolio?portfolio=10445739", [["CVS", "$180.32", "9.30%"]]], "5ahujaalisha": [102000.91, "https://www.investopedia.com/simulator/games/user-portfolio?portfolio=10445740", [["APD", "$5,016.75", "1.22%"], ["COIN", "$6,209.40", "-3.94%"], ["HSY", "$5,272.50", "1.88%"], ["KALU", "$4,218.50", "1.81%"], ["META", "$8,411.85", "0.67%"], ["ULTA", "$6,200.24", "1.07%"]]], "5lucaslloyd": [117697.74, "https://www.investopedia.com/simulator/games/user-portfolio?portfolio=10445741", [["CONL", "$11,265.90", "84.14%"], ["DKNG", "$12,468.55", "25.61%"], ["MODG", "$7,818.71", "-21.84%"], ["NVDL", "$11,326.40", "9.62%"], ["PLTR", "$30,293.21", "102.70%"], ["QQQ", "$6,578.00", "7.09%"], ["SOXL", "$7,362.50", "-25.03%"], ["SSO", "$23,154.00", "13.94%"], ["UBER", "$146.30", "-0.52%"]]], "5afzalzadehlaily": [103862.46, "https://www.investopedia.com/simulator/games/user-portfolio?portfolio=10445742", [["AMD", "$4,653.00", "-7.67%"], ["BAC", "$5,722.20", "11.19%"], ["BMY", "$5,466.54", "10.07%"], ["INTC", "$5,643.38", "17.69%"], ["NVDA", "$5,615.31", "7.22%"], ["UNH", "$5,426.01", "1.82%"], ["VOO", "$52,708.70", "3.42%"]]], "5sheaffermalia": [108728.95, "https://www.investopedia.com/simulator/games/user-portfolio?portfolio=10445743", [["BND", "$292.98", "-1.87%"], ["BRK.B", "$21,524.40", "8.34%"], ["COST", "$21,960.40", "10.35%"], ["NVDA", "$23,283.01", "16.98%"], ["SO", "$19,912.39", "1.01%"], ["SPY", "$21,500.64", "7.12%"]]], "5smithmarco": [102277.77, "https://www.investopedia.com/simulator/games/user-portfolio?portfolio=10445744", [["UBER", "$2,926.00", "0.93%"], ["UNP", "$14,965.20", "0.56%"]]], "5yoshioka-meonskebradley": [112362.66, "https://www.investopedia.com/simulator/games/user-portfolio?portfolio=10445745", [["AAPL", "$5,755.75", "2.22%"], ["ASML", "$13,648.30", "0.94%"], ["CRWD", "$51,103.34", "19.90%"], ["CSCO", "$10,407.66", "6.48%"], ["DIS", "$115.56", "34.06%"], ["MCD", "$1,181.14", "9.07%"], ["MSFT", "$8,333.40", "0.19%"], ["RSPA", "$9,117.72", "3.65%"], ["VOOG", "$12,569.73", "6.60%"]]], "5garciaocran": [108509.06, "https://www.investopedia.com/simulator/games/user-portfolio?portfolio=10445746", [["AAPL", "$4,604.60", "2.82%"], ["BAC", "$6,199.05", "23.60%"], ["DIS", "$5,778.00", "29.90%"], ["LOAR", "$7,265.20", "35.02%"], ["NKE", "$3,965.00", "-4.32%"], ["NVDA", "$6,847.95", "12.32%"]]], "5telikepallisharvil": [90675.62, "https://www.investopedia.com/simulator/games/user-portfolio?portfolio=10445747", [["AMD", "$14,100.00", "-3.11%"], ["DJT", "$46,466.10", "-17.54%"], ["MSFT", "$4,166.70", "-0.75%"], ["NOC", "$9,612.00", "-4.76%"], ["NVDA", "$10,956.71", "5.34%"], ["WMT", "$4,462.75", "17.90%"]]], "5bisharajeries": [122240.13, "https://www.investopedia.com/simulator/games/user-portfolio?portfolio=10445748", []], "5jianglin": [109627.5, "https://www.investopedia.com/simulator/games/user-portfolio?portfolio=10445749", [["HYG", "$9,978.13", "1.75%"], ["ROKU", "$31,324.92", "-0.04%"], ["SHOP", "$16,755.00", "57.21%"], ["VOO", "$43,923.92", "8.68%"]]], "5qinsophia": [101391.38, "https://www.investopedia.com/simulator/games/user-portfolio?portfolio=10445750", [["AMD", "$5,640.00", "-8.51%"], ["ASML", "$6,822.65", "-23.13%"], ["CRWD", "$10,873.05", "38.75%"], ["GOOG", "$1,016.28", "3.15%"], ["MSFT", "$5,000.04", "0.45%"], ["NVDA", "$1,369.59", "15.55%"]]], "kayanshah": [106905.09, "https://www.investopedia.com/simulator/games/user-portfolio?portfolio=10445751", [["ADBE", "$10,339.40", "-4.90%"], ["BRK.B", "$2,390.35", "2.43%"], ["GOOG", "$6,775.20", "3.89%"], ["KB", "$7,702.20", "6.28%"], ["META", "$11,215.80", "6.14%"], ["NVDA", "$8,217.53", "7.79%"], ["PLTR", "$5,145.34", "49.24%"], ["SPY", "$50,166.48", "8.30%"], ["UCO", "$490.01", "-12.59%"], ["WLDN", "$4,285.71", "1.22%"]]], "5kimben": [100468.9, "https://www.investopedia.com/simulator/games/user-portfolio?portfolio=10445753", []], "helllloo11": [107393.05, "https://www.investopedia.com/simulator/games/user-portfolio?portfolio=10445754", [["AMD", "$65,424.00", "-5.14%"], ["LUNR", "$21,393.40", "-6.08%"], ["TQQQ", "$20,472.81", "6.09%"]]], "5wangwei": [110942.34, "https://www.investopedia.com/simulator/games/user-portfolio?portfolio=10445759", [["AAPL", "$1,841.84", "2.61%"], ["ADSK", "$319.18", "17.51%"], ["AMZN", "$201.12", "6.20%"], ["BA", "$38,271.25", "8.91%"], ["CAT", "$812.33", "4.46%"], ["COST", "$2,863.83", "5.42%"], ["DESP", "$891.00", "2.24%"], ["DIS", "$115.54", "26.37%"], ["DJT", "$151.85", "-43.50%"], ["DRS", "$17,734.90", "11.09%"], ["DUOL", "$9,265.05", "23.51%"], ["ENVA", "$1,075.95", "21.15%"], ["GOOG", "$507.93", "3.89%"], ["GOOGL", "$838.10", "-0.07%"], ["INTC", "$754.80", "3.54%"], ["JPM", "$1,753.29", "11.22%"], ["MA", "$2,625.35", "3.45%"], ["MSTR", "$12,095.16", "-0.77%"], ["NVDA", "$2,054.38", "6.65%"], ["SPOT", "$4,733.60", "25.29%"], ["TQQQ", "$313.76", "13.43%"], ["TSLA", "$11,080.32", "10.50%"], ["XOM", "$602.15", "1.56%"]]], "5vincentchung": [100386.96, "https://www.investopedia.com/simulator/games/user-portfolio?portfolio=10445767", [["AAPL", "$7,606.50", "2.33%"], ["META", "$10,091.40", "-6.40%"], ["MSFT", "$10,416.75", "-4.53%"], ["NFLX", "$7,794.95", "6.21%"], ["NVDA", "$17,941.62", "-2.87%"], ["SPOT", "$7,573.76", "2.76%"]]], "1enriquezmario": [196187.13, "https://www.investopedia.com/simulator/games/user-portfolio?portfolio=10445928", [["LUNR", "$195,128.05", "59.93%"]]], "2laumei": [110376.43, "https://www.investopedia.com/simulator/games/user-portfolio?portfolio=10447810", [["AMZN", "$20,112.00", "0.92%"], ["JPM", "$10,774.08", "0.23%"], ["LLY", "$3,000.72", "-19.03%"], ["TGT", "$19,756.50", "2.84%"], ["TSLA", "$15,247.76", "47.02%"]]], "2bumanlagjacob": [95776.63, "https://www.investopedia.com/simulator/games/user-portfolio?portfolio=10447811", [["IRM", "$38,071.68", "-1.04%"], ["TT", "$20,731.75", "4.47%"], ["WAB", "$19,964.50", "5.04%"]]], "2tavakoliariana": [105000.28, "https://www.investopedia.com/simulator/games/user-portfolio?portfolio=10447812", [["AAPL", "$3,683.68", "4.12%"], ["COST", "$5,728.80", "10.75%"], ["LUNR", "$722.75", "21.01%"], ["NFLX", "$4,328.75", "31.30%"], ["NVDA", "$6,847.95", "14.80%"], ["QQQ", "$7,084.00", "9.60%"], ["SMH", "$731.82", "3.44%"], ["TSLA", "$1,732.70", "5.42%"], ["VOO", "$10,981.60", "8.37%"], ["WMT", "$3,123.93", "5.92%"], ["WOK", "$173.10", "-20.96%"]]], "2ambrizcaden": [103618.33, "https://www.investopedia.com/simulator/games/user-portfolio?portfolio=10447813", [["AAPL", "$5,755.75", "4.12%"], ["AMZN", "$3,016.80", "18.60%"], ["ANF", "$2,519.84", "-1.37%"], ["BRK.B", "$6,218.16", "2.88%"], ["COST", "$8,591.49", "5.78%"], ["CSCO", "$1,344.81", "16.03%"], ["LULU", "$12,465.52", "32.20%"], ["SPGI", "$8,813.31", "-0.03%"], ["TGT", "$4,342.80", "-11.46%"], ["ULTA", "$5,821.04", "-4.64%"]]], "2akramzaara": [103085.39, "https://www.investopedia.com/simulator/games/user-portfolio?portfolio=10447815", [["AAPL", "$4,604.60", "4.11%"], ["AMGN", "$2,069.34", "-9.52%"], ["AMZN", "$1,004.60", "13.71%"], ["AXP", "$1,221.52", "21.43%"], ["COST", "$3,819.20", "10.70%"], ["CSCO", "$467.76", "17.75%"], ["LLY", "$4,501.08", "-20.76%"], ["LULU", "$2,624.32", "25.80%"], ["MRCY", "$820.40", "3.53%"], ["NFLX", "$6,060.25", "30.98%"], ["NVDA", "$17,804.66", "9.13%"], ["PANW", "$3,858.95", "3.62%"]]], "2quachisis": [100744.97, "https://www.investopedia.com/simulator/games/user-portfolio?portfolio=10447816", [["AAPL", "$5,755.75", "1.80%"], ["RBLX", "$243.13", "11.22%"]]], "2greenesal": [99699.37, "https://www.investopedia.com/simulator/games/user-portfolio?portfolio=10447817", [["AAPL", "$18,418.40", "2.21%"], ["AXP", "$9,161.40", "12.86%"], ["COST", "$4,773.05", "6.27%"], ["HD", "$4,274.45", "6.13%"], ["NVDA", "$15,065.48", "0.26%"], ["PLTR", "$1,286.34", "47.09%"], ["RDDT", "$2,098.13", "20.06%"], ["WMT", "$4,462.75", "11.08%"]]], "2mirilily": [112172.67, "https://www.investopedia.com/simulator/games/user-portfolio?portfolio=10447818", [["ANET", "$5,957.40", "11.92%"], ["GE", "$7,913.40", "5.23%"], ["HWKN", "$8,527.05", "14.42%"], ["ISRG", "$8,056.50", "11.20%"], ["LLY", "$3,750.90", "-19.52%"], ["META", "$5,607.90", "5.43%"], ["PANW", "$5,788.43", "10.67%"], ["RCL", "$11,037.93", "49.23%"], ["SPOT", "$9,940.56", "39.86%"], ["SPY", "$11,944.40", "6.59%"], ["UBER", "$5,852.00", "-1.21%"], ["VGT", "$18,622.20", "7.72%"]]], "2chobanianbella": [103314.47, "https://www.investopedia.com/simulator/games/user-portfolio?portfolio=10447819", [["AAPL", "$4,610.00", "2.77%"], ["AMZN", "$5,028.00", "5.18%"], ["COST", "$2,863.83", "9.08%"], ["GOOG", "$3,387.60", "1.50%"], ["LULU", "$3,280.40", "25.67%"], ["NVDA", "$6,165.77", "7.93%"], ["TSLA", "$3,465.40", "61.45%"]]], "2andersonrhys": [105402.26, "https://www.investopedia.com/simulator/games/user-portfolio?portfolio=10447820", [["AAPL", "$15,213.00", "2.69%"], ["CRWD", "$6,529.23", "36.96%"], ["LEVI", "$9,123.95", "-9.13%"], ["NVDA", "$5,480.69", "13.55%"]]], "2hajizadehyasmin": [102292.85, "https://www.investopedia.com/simulator/games/user-portfolio?portfolio=10447821", [["AAPL", "$1,151.15", "2.01%"], ["AMZN", "$2,009.20", "13.05%"], ["DIS", "$2,773.44", "31.96%"], ["NVDA", "$13,695.89", "8.25%"], ["RBLX", "$972.50", "22.40%"]]], "2habibvandarion": [103633.61, "https://www.investopedia.com/simulator/games/user-portfolio?portfolio=10447822", [["AMD", "$7,040.00", "-5.02%"], ["AMZN", "$10,056.00", "13.66%"], ["GOOG", "$8,469.00", "2.20%"], ["NVDA", "$13,701.72", "8.98%"], ["TSM", "$9,229.50", "7.81%"]]], "2santosshin": [112780.72, "https://www.investopedia.com/simulator/games/user-portfolio?portfolio=10447823", [["BE", "$10,657.92", "8.55%"], ["LMND", "$4,995.06", "-0.04%"], ["SMCI", "$3,442.30", "16.04%"], ["SMMT", "$4,871.30", "-3.01%"]]], "2urvizoefrain": [108838.91, "https://www.investopedia.com/simulator/games/user-portfolio?portfolio=10447824", []], "2dersecamren": [116075.5, "https://www.investopedia.com/simulator/games/user-portfolio?portfolio=10447825", [["AAPL", "$5,065.06", "-1.90%"], ["ADMA", "$1,080.50", "39.69%"], ["AMZN", "$7,240.32", "7.14%"], ["APP", "$5,780.70", "96.48%"], ["AUR", "$128.70", "28.70%"], ["CHDN", "$3,131.70", "5.35%"], ["CLOV", "$234.84", "-7.97%"], ["COST", "$47,740.00", "5.80%"], ["CYBN", "$234.74", "17.84%"], ["DAVE", "$2,899.35", "102.75%"], ["DJT", "$912.30", "-17.95%"], ["EA", "$821.48", "12.25%"], ["JPM", "$8,769.60", "11.53%"], ["LULU", "$13,121.60", "11.74%"], ["NKE", "$3,166.40", "-1.94%"], ["OUT", "$579.30", "5.81%"], ["SKYT", "$1,346.95", "-11.79%"], ["SOFI", "$629.24", "49.56%"], ["SPGI", "$8,294.88", "4.68%"], ["SWK", "$2,044.68", "-13.05%"], ["WOK", "$115.40", "-20.96%"]]], "2whitecaden": [100687.25, "https://www.investopedia.com/simulator/games/user-portfolio?portfolio=10447826", [["ADBE", "$15,509.10", "-2.70%"], ["DKS", "$7,567.35", "-0.18%"], ["IREN", "$10,375.00", "-10.71%"], ["LLY", "$22,505.40", "-10.28%"], ["NBIX", "$7,596.90", "3.95%"], ["PANW", "$27,012.65", "-0.32%"]]], "2baradlayannie": [104128.05, "https://www.investopedia.com/simulator/games/user-portfolio?portfolio=10447827", [["AAPL", "$53,413.36", "2.50%"], ["CART", "$216.75", "17.00%"], ["CAT", "$1,624.66", "17.58%"], ["COST", "$5,728.80", "10.69%"], ["DUOL", "$11,323.95", "22.00%"], ["HD", "$855.31", "15.15%"], ["JNJ", "$5,142.89", "-1.65%"], ["NCLH", "$1,363.00", "11.93%"], ["RBLX", "$6,434.34", "14.33%"], ["ROKU", "$206.09", "-0.17%"], ["TGT", "$2,632.00", "-15.43%"], ["WMT", "$1,785.10", "8.42%"]]], "2freyolivia": [94877.33, "https://www.investopedia.com/simulator/games/user-portfolio?portfolio=10447828", [["AAPL", "$2,302.30", "-0.57%"], ["AMAT", "$17,470.39", "-15.60%"], ["LLY", "$15,003.60", "-18.65%"], ["LULU", "$32,813.00", "14.33%"], ["NVDA", "$13,695.89", "8.28%"], ["RKLB", "$12,015.90", "253.89%"], ["SG", "$651.75", "12.93%"], ["VOO", "$549.05", "-0.16%"]]], "2gibsonjacob": [108409.91, "https://www.investopedia.com/simulator/games/user-portfolio?portfolio=10447829", [["AAPL", "$10,360.35", "4.12%"], ["AMZN", "$4,424.64", "18.54%"], ["LULU", "$8,203.25", "35.60%"], ["NVDA", "$41,087.67", "14.86%"], ["PEP", "$2,431.50", "-5.94%"]]], "2neubertsophia": [101061.66, "https://www.investopedia.com/simulator/games/user-portfolio?portfolio=10447830", [["ANET", "$3,971.60", "14.39%"], ["GE", "$3,599.20", "2.38%"], ["LULU", "$8,203.25", "24.91%"], ["LUNR", "$216.83", "2.81%"], ["PGR", "$3,960.30", "9.81%"]]], "brandens": [117217.8, "https://www.investopedia.com/simulator/games/user-portfolio?portfolio=10447831", [["AAPL", "$1,151.15", "4.11%"], ["AMZN", "$1,205.52", "18.45%"], ["BROS", "$104.02", "48.30%"], ["CMG", "$31,072.50", "17.70%"], ["FLNC", "$11,715.00", "39.71%"], ["GE", "$8,998.00", "5.30%"], ["MSFT", "$14,583.45", "-0.23%"], ["NIO", "$657.15", "-18.24%"], ["NVDA", "$20,406.88", "17.66%"], ["TSLA", "$22,506.90", "54.80%"], ["WOK", "$57.70", "-20.96%"]]], "2chenkhai": [110921.42, "https://www.investopedia.com/simulator/games/user-portfolio?portfolio=10447832", [["ABNB", "$4,175.10", "20.32%"], ["BBWI", "$4,336.80", "5.30%"], ["COST", "$5,727.66", "8.81%"], ["CVS", "$2,404.20", "3.86%"], ["F", "$4,014.50", "3.38%"], ["INTC", "$1,509.60", "5.09%"], ["KSS", "$3,697.00", "-4.57%"], ["LULU", "$3,937.56", "22.89%"], ["MSI", "$1,469.13", "14.85%"], ["NFLX", "$6,928.84", "4.24%"], ["NKE", "$4,749.60", "-4.49%"], ["RDDT", "$12,588.75", "137.16%"], ["TGT", "$4,737.60", "-3.73%"], ["UPS", "$2,750.70", "7.17%"]]], "2petergeorge": [118780.55, "https://www.investopedia.com/simulator/games/user-portfolio?portfolio=10447833", []], "2alexialee": [98105.57, "https://www.investopedia.com/simulator/games/user-portfolio?portfolio=10447834", []], "2daosean": [103572.97, "https://www.investopedia.com/simulator/games/user-portfolio?portfolio=10447838", [["AAPL", "$5,301.50", "4.19%"], ["JPM", "$6,261.75", "21.77%"], ["NKE", "$4,361.50", "1.65%"], ["NVDA", "$7,672.96", "7.15%"], ["SPGI", "$10,887.03", "5.10%"]]], "2wuchristopher": [100003.66, "https://www.investopedia.com/simulator/games/user-portfolio?portfolio=10447839", [["AAPL", "$27,627.60", "2.40%"], ["AMD", "$2,820.00", "-6.42%"], ["GOOGL", "$1,172.85", "3.88%"], ["NVDA", "$43,552.93", "3.66%"], ["SWBI", "$1,381.00", "-5.93%"], ["TSM", "$13,851.00", "6.36%"], ["TTWO", "$9,420.50", "29.48%"]]], "2continichris": [133014.95, "https://www.investopedia.com/simulator/games/user-portfolio?portfolio=10447845", []], "2eberhartsavannah": [99831.86, "https://www.investopedia.com/simulator/games/user-portfolio?portfolio=10447853", [["APP", "$1,284.60", "-5.02%"], ["DUOL", "$1,372.60", "5.04%"], ["EA", "$657.18", "-1.53%"], ["IBM", "$903.96", "6.60%"], ["NFLX", "$3,463.00", "-1.82%"]]], "2phamjinny": [110733.21, "https://www.investopedia.com/simulator/games/user-portfolio?portfolio=10447859", [["AAPL", "$5,065.06", "2.09%"], ["AMZN", "$6,033.60", "13.17%"], ["COST", "$9,546.10", "9.57%"], ["MSFT", "$6,250.05", "-0.47%"], ["NVDA", "$6,847.95", "10.97%"], ["PACS", "$1,956.00", "-60.12%"], ["RDDT", "$13,987.50", "137.16%"], ["TSLA", "$9,002.76", "60.76%"]]], "2nguyenthien": [108101.47, "https://www.investopedia.com/simulator/games/user-portfolio?portfolio=10447866", [["NVDA", "$36,157.15", "-2.87%"], ["TT", "$65,122.03", "10.88%"], ["TTWO", "$6,594.35", "28.34%"]]], "2sepelucas": [111447.42, "https://www.investopedia.com/simulator/games/user-portfolio?portfolio=10448346", [["LB", "$1,485.10", "111.61%"], ["LULU", "$3,281.30", "19.47%"], ["LUNR", "$28,910.00", "25.78%"], ["SPYG", "$53,915.63", "7.97%"]]], "6slacklucas": [82560.48, "https://www.investopedia.com/simulator/games/user-portfolio?portfolio=10449067", [["AMZN", "$5,028.00", "7.28%"], ["DJT", "$69,699.95", "-8.31%"], ["NVDA", "$2,739.18", "0.25%"], ["WMT", "$5,176.79", "12.00%"]]], "6ishiguronobuhisa": [96126.43, "https://www.investopedia.com/simulator/games/user-portfolio?portfolio=10449068", [["AAPL", "$69,069.00", "3.87%"], ["SPGI", "$26,439.93", "1.33%"]]], "6faureian": [97857.36, "https://www.investopedia.com/simulator/games/user-portfolio?portfolio=10449069", [["AAPL", "$4,604.60", "2.82%"], ["AMZN", "$6,027.60", "0.98%"], ["AVGO", "$817.33", "-6.43%"], ["DIS", "$19,067.40", "4.80%"], ["F", "$229.30", "10.24%"], ["LMT", "$12,438.12", "-8.48%"], ["NFLX", "$17,315.00", "3.84%"], ["NOC", "$15,859.80", "-8.81%"], ["NVDA", "$9,591.20", "9.07%"], ["SHEL", "$978.60", "-5.22%"]]], "6choierica": [100064.08, "https://www.investopedia.com/simulator/games/user-portfolio?portfolio=10449070", [["AMZN", "$402.24", "13.22%"], ["JNJ", "$311.50", "-2.33%"], ["MCD", "$1,477.70", "2.17%"], ["MSFT", "$833.50", "-0.53%"], ["NVDA", "$411.05", "10.25%"]]], "6nagpurwalafayezah": [105924.34, "https://www.investopedia.com/simulator/games/user-portfolio?portfolio=10449071", [["AAPL", "$2,302.30", "-1.84%"], ["HRB", "$4,790.48", "-10.87%"], ["MSFT", "$2,083.35", "-3.41%"], ["NOW", "$2,106.59", "-0.29%"], ["NVDA", "$2,739.18", "-5.32%"]]], "ufatalo": [96080.08, "https://www.investopedia.com/simulator/games/user-portfolio?portfolio=10449072", [["AAPL", "$11,511.50", "2.29%"], ["AMZN", "$1,004.60", "14.90%"], ["GOOG", "$1,693.80", "4.42%"], ["NVDA", "$136.96", "15.32%"], ["OSTX", "$4,030.00", "-50.85%"]]], "6ubrychfilip_": [120525.7, "https://www.investopedia.com/simulator/games/user-portfolio?portfolio=10449073", [["FTV", "$95,940.00", "0.14%"], ["MSTX", "$3,425.40", "4.32%"], ["SPY", "$20,903.40", "0.01%"]]], "6claypillora": [102656.41, "https://www.investopedia.com/simulator/games/user-portfolio?portfolio=10449074", [["AAPL", "$5,065.06", "2.00%"], ["AMZN", "$11,664.96", "12.00%"], ["COST", "$14,322.00", "6.37%"], ["MCD", "$20,079.38", "3.46%"], ["MSFT", "$2,083.35", "0.49%"], ["NVDA", "$5,341.40", "8.46%"], ["SBUX", "$4,089.20", "12.07%"], ["TGT", "$3,948.00", "-13.06%"]]], "6valsalon": [103139.14, "https://www.investopedia.com/simulator/games/user-portfolio?portfolio=10449075", [["BA", "$15,308.50", "1.30%"], ["DUOL", "$17,157.50", "-4.55%"], ["NFLX", "$12,986.25", "3.85%"], ["TSLA", "$12,119.10", "15.75%"], ["ULTA", "$10,186.82", "-2.65%"], ["WMT", "$29,908.80", "9.59%"]]], "6cardenasdayanara": [107534.24, "https://www.investopedia.com/simulator/games/user-portfolio?portfolio=10449076", [["AFRM", "$10,455.75", "78.23%"], ["BRK.B", "$5,261.52", "3.72%"], ["CRWD", "$6,891.97", "34.45%"], ["NVDA", "$5,889.23", "15.32%"], ["TSLA", "$8,656.50", "68.89%"]]], "6luosicheng": [104697.52, "https://www.investopedia.com/simulator/games/user-portfolio?portfolio=10449077", [["AAPL", "$3,453.45", "-0.14%"], ["AMZN", "$1,004.60", "0.80%"], ["COST", "$9,548.00", "4.21%"], ["WOK", "$5.77", "-24.87%"]]], "6chaocaleb": [103232.25, "https://www.investopedia.com/simulator/games/user-portfolio?portfolio=10449078", [["DUOL", "$102,945.00", "1.77%"]]], "6xusophie": [115487.7, "https://www.investopedia.com/simulator/games/user-portfolio?portfolio=10449079", [["BA", "$2,757.24", "-12.30%"], ["DB", "$10,533.38", "5.36%"], ["GOOG", "$21,850.01", "1.09%"], ["RTX", "$4,977.00", "0.14%"], ["TGT", "$6,974.80", "-9.57%"], ["UAL", "$22,804.40", "127.90%"]]], "6hernandezbrady": [132939.61, "https://www.investopedia.com/simulator/games/user-portfolio?portfolio=10449080", []], "6saishyamrugoobur": [109726.42, "https://www.investopedia.com/simulator/games/user-portfolio?portfolio=10449081", [["AAPL", "$33,383.35", "1.77%"], ["AMZN", "$12,067.20", "13.82%"], ["GOOGL", "$10,890.75", "0.70%"], ["HD", "$12,823.35", "16.88%"], ["MSFT", "$10,416.75", "0.07%"], ["NVDA", "$19,585.12", "11.29%"], ["TSLA", "$10,387.80", "57.34%"]]], "6sophiamovassate": [111350.14, "https://www.investopedia.com/simulator/games/user-portfolio?portfolio=10449082", [["AMZN", "$20,092.00", "12.83%"], ["BAC", "$6,823.96", "23.08%"], ["DIS", "$15,482.37", "26.98%"], ["NVDA", "$13,701.72", "-7.84%"], ["PGR", "$5,280.40", "8.60%"], ["RBLX", "$16,232.09", "13.37%"], ["SPOT", "$12,780.72", "37.95%"], ["YUMC", "$19,509.85", "42.13%"]]], "6lopesdebritorayane": [98969.88, "https://www.investopedia.com/simulator/games/user-portfolio?portfolio=10449084", [["AAPL", "$2,302.30", "2.00%"], ["AMZN", "$3,016.80", "13.22%"], ["DIS", "$2,195.26", "26.37%"], ["MSFT", "$8,333.40", "-2.77%"], ["NVDA", "$13,421.97", "-3.09%"], ["RBLX", "$24,226.27", "-3.53%"]]], "seyeong": [103080.22, "https://www.investopedia.com/simulator/games/user-portfolio?portfolio=10449138", [["AAPL", "$4,379.50", "2.04%"], ["ADBE", "$516.51", "-0.86%"], ["AMZN", "$4,424.64", "11.64%"], ["JNJ", "$1,090.25", "1.17%"], ["MSFT", "$1,250.25", "0.18%"], ["TSLA", "$4,501.38", "57.16%"], ["V", "$1,557.45", "16.57%"]]], "unknovus": [139401.83, "https://www.investopedia.com/simulator/games/user-portfolio?portfolio=10450904", []], "p3_horvath_levente": [103885.02, "https://www.investopedia.com/simulator/games/user-portfolio?portfolio=10451510", [["AAPL", "$23,023.00", "2.32%"], ["AMZN", "$10,046.00", "13.23%"], ["NNE", "$5,138.00", "-15.63%"], ["NVDA", "$13,701.72", "9.88%"], ["TT", "$2,903.53", "2.61%"]]], "5shihcalista": [81306.77, "https://www.investopedia.com/simulator/games/user-portfolio?portfolio=10452002", [["SMCI", "$80,367.00", "-11.84%"]]], "2gaudaanvi": [108211.81, "https://www.investopedia.com/simulator/games/user-portfolio?portfolio=10453457", [["AAPL", "$1,151.15", "2.03%"], ["BLK", "$2,079.12", "19.56%"], ["CCJ", "$1,458.50", "36.79%"], ["CLSK", "$2,968.00", "23.36%"], ["ORCL", "$5,674.35", "37.32%"], ["QQQ", "$22,271.92", "12.76%"], ["VOO", "$43,374.87", "6.94%"]]], "2symmonsnatalie": [102237.32, "https://www.investopedia.com/simulator/games/user-portfolio?portfolio=10453458", [["AAPL", "$9,209.20", "1.72%"], ["F", "$4,581.40", "10.18%"], ["LULU", "$9,843.90", "26.44%"], ["NKE", "$4,749.60", "-5.33%"]]], "6mamarianrubyna": [102169.61, "https://www.investopedia.com/simulator/games/user-portfolio?portfolio=10480692", []], "all_in_tqqq": [102456.23, "https://www.investopedia.com/simulator/games/user-portfolio?portfolio=10701005", [["TQQQ", "$102,422.66", "2.46%"]]]}